Workbook

Sheet Assurance Dashboard
B1: API SECURITY TESTING BIBLE
B3: Execution-ready assurance | Candidate → Applicable → Ready → Validate → Remediate → Retest → Close
B5: READINESS RULE • A test is Ready only when applicability, preconditions, identities, data, environment, endpoint/component, safety limits, evidence capture and operational ownership are confirmed. A Passed or Failed result requires observed evidence.
B8: TOTAL TESTS | D8: CRITICAL + HIGH | G8: READY | I8: VALIDATED | L8: OPEN FAILURES
B9: =COUNTA('Security Test Catalogue'!$C$2:$C$484) -> 483 | D9: =COUNTIF('Security Test Catalogue'!$BA$2:$BA$484,"Critical")+COUNTIF('Security Test Catalogue'!$BA$2:$BA$484,"High") -> 267 | G9: =COUNTIF('Security Test Catalogue'!$BD$2:$BD$484,"Ready") -> 0 | I9: =COUNTIF('Security Test Catalogue'!$BD$2:$BD$484,"Passed")+COUNTIF('Security Test Catalogue'!$BD$2:$BD$484,"Failed") -> 0 | L9: =COUNTIF('Security Test Catalogue'!$BD$2:$BD$484,"Failed")+COUNTIF('Security Test Catalogue'!$BD$2:$BD$484,"Remediation in Progress") -> 0
B11: All tests in the bible | D11: Priority risk coverage | G11: All execution prerequisites met | I11: Evidence-backed outcomes | L11: Failure or active remediation
B13: 1 EXECUTION READINESS AND OUTCOMES
B14: Separate planning, readiness, active execution, control outcome and closure. This prevents catalogue completeness being mistaken for assurance.
B16: Lifecycle state | C16: Count | D16: % of catalogue | G16: Ready gate requirement | H16: Required evidence | L16: Result | M16: Minimum decision rule
B17: Candidate | C17: =COUNTIF('Security Test Catalogue'!$BD$2:$BD$484,B17) -> 483 | D17: =IFERROR(C17/$C$29,0) -> 1 | G17: Scope | H17: Authorisation, environment and exact surface | L17: Passed | M17: Expected protection observed with complete evidence.
B18: Applicable | C18: =COUNTIF('Security Test Catalogue'!$BD$2:$BD$484,B18) -> 0 | D18: =IFERROR(C18/$C$29,0) -> 0 | G18: Applicability | H18: Decision and rationale | L18: Failed | M18: Defined failure condition reproduced or control absent.
B19: Ready | C19: =COUNTIF('Security Test Catalogue'!$BD$2:$BD$484,B19) -> 0 | D19: =IFERROR(C19/$C$29,0) -> 0 | G19: Identity | H19: Test and comparison roles available | L19: Blocked | M19: Prerequisite or dependency prevented a valid decision.
B20: In Progress | C20: =COUNTIF('Security Test Catalogue'!$BD$2:$BD$484,B20) -> 0 | D20: =IFERROR(C20/$C$29,0) -> 0 | G20: Data | H20: Synthetic boundary data prepared | L20: Risk Accepted | M20: Approved exception, expiry and compensating control recorded.
B21: Passed | C21: =COUNTIF('Security Test Catalogue'!$BD$2:$BD$484,B21) -> 0 | D21: =IFERROR(C21/$C$29,0) -> 0 | G21: Baseline | H21: Authorised success captured | L21: Closed | M21: Remediation retested or accepted closure evidence exists.
B22: Failed | C22: =COUNTIF('Security Test Catalogue'!$BD$2:$BD$484,B22) -> 0 | D22: =IFERROR(C22/$C$29,0) -> 0 | G22: Safety | H22: Limits, stop and rollback agreed
B23: Blocked | C23: =COUNTIF('Security Test Catalogue'!$BD$2:$BD$484,B23) -> 0 | D23: =IFERROR(C23/$C$29,0) -> 0 | G23: Observability | H23: Evidence and logs available
B24: Remediation in Progress | C24: =COUNTIF('Security Test Catalogue'!$BD$2:$BD$484,B24) -> 0 | D24: =IFERROR(C24/$C$29,0) -> 0 | G24: Ownership | H24: Operational and remediation contacts
B25: Ready for Retest | C25: =COUNTIF('Security Test Catalogue'!$BD$2:$BD$484,B25) -> 0 | D25: =IFERROR(C25/$C$29,0) -> 0
B26: Closed | C26: =COUNTIF('Security Test Catalogue'!$BD$2:$BD$484,B26) -> 0 | D26: =IFERROR(C26/$C$29,0) -> 0
B27: Risk Accepted | C27: =COUNTIF('Security Test Catalogue'!$BD$2:$BD$484,B27) -> 0 | D27: =IFERROR(C27/$C$29,0) -> 0
B28: Not Applicable | C28: =COUNTIF('Security Test Catalogue'!$BD$2:$BD$484,B28) -> 0 | D28: =IFERROR(C28/$C$29,0) -> 0
B29: Total | C29: =SUM(C17:C28) -> 483 | D29: =SUM(D17:D28) -> 1
B31: 2 SECURITY DOMAIN COVERAGE
B32: Completion is based on evidence-backed Passed or Failed outcomes, not on catalogue population.
B34: Security domain | C34: Total | D34: Critical | E34: High | F34: Ready | G34: Validated | H34: Failed | I34: Completion
B35: 1. Identity, Authentication & Session | C35: =COUNTIF('Security Test Catalogue'!$A$2:$A$484,B35) -> 79 | D35: =COUNTIFS('Security Test Catalogue'!$A$2:$A$484,B35,'Security Test Catalogue'!$BA$2:$BA$484,"Critical") -> 2 | E35: =COUNTIFS('Security Test Catalogue'!$A$2:$A$484,B35,'Security Test Catalogue'!$BA$2:$BA$484,"High") -> 74 | F35: =COUNTIFS('Security Test Catalogue'!$A$2:$A$484,B35,'Security Test Catalogue'!$BD$2:$BD$484,"Ready") -> 0 | G35: =COUNTIFS('Security Test Catalogue'!$A$2:$A$484,B35,'Security Test Catalogue'!$BD$2:$BD$484,"Passed")+COUNTIFS('Security Test Catalogue'!$A$2:$A$484,B35,'Security Test Catalogue'!$BD$2:$BD$484,"Failed") -> 0 | H35: =COUNTIFS('Security Test Catalogue'!$A$2:$A$484,B35,'Security Test Catalogue'!$BD$2:$BD$484,"Failed") -> 0 | I35: =IFERROR(G35/C35,0) -> 0
B36: 2. Record & Tenant Access (BOLA / IDOR) | C36: =COUNTIF('Security Test Catalogue'!$A$2:$A$484,B36) -> 22 | D36: =COUNTIFS('Security Test Catalogue'!$A$2:$A$484,B36,'Security Test Catalogue'!$BA$2:$BA$484,"Critical") -> 9 | E36: =COUNTIFS('Security Test Catalogue'!$A$2:$A$484,B36,'Security Test Catalogue'!$BA$2:$BA$484,"High") -> 11 | F36: =COUNTIFS('Security Test Catalogue'!$A$2:$A$484,B36,'Security Test Catalogue'!$BD$2:$BD$484,"Ready") -> 0 | G36: =COUNTIFS('Security Test Catalogue'!$A$2:$A$484,B36,'Security Test Catalogue'!$BD$2:$BD$484,"Passed")+COUNTIFS('Security Test Catalogue'!$A$2:$A$484,B36,'Security Test Catalogue'!$BD$2:$BD$484,"Failed") -> 0 | H36: =COUNTIFS('Security Test Catalogue'!$A$2:$A$484,B36,'Security Test Catalogue'!$BD$2:$BD$484,"Failed") -> 0 | I36: =IFERROR(G36/C36,0) -> 0
B37: 3. Privilege & Function Boundaries (BFLA) | C37: =COUNTIF('Security Test Catalogue'!$A$2:$A$484,B37) -> 35 | D37: =COUNTIFS('Security Test Catalogue'!$A$2:$A$484,B37,'Security Test Catalogue'!$BA$2:$BA$484,"Critical") -> 5 | E37: =COUNTIFS('Security Test Catalogue'!$A$2:$A$484,B37,'Security Test Catalogue'!$BA$2:$BA$484,"High") -> 27 | F37: =COUNTIFS('Security Test Catalogue'!$A$2:$A$484,B37,'Security Test Catalogue'!$BD$2:$BD$484,"Ready") -> 0 | G37: =COUNTIFS('Security Test Catalogue'!$A$2:$A$484,B37,'Security Test Catalogue'!$BD$2:$BD$484,"Passed")+COUNTIFS('Security Test Catalogue'!$A$2:$A$484,B37,'Security Test Catalogue'!$BD$2:$BD$484,"Failed") -> 0 | H37: =COUNTIFS('Security Test Catalogue'!$A$2:$A$484,B37,'Security Test Catalogue'!$BD$2:$BD$484,"Failed") -> 0 | I37: =IFERROR(G37/C37,0) -> 0
B38: 4. Field, Property & Payload Authorisation | C38: =COUNTIF('Security Test Catalogue'!$A$2:$A$484,B38) -> 34 | D38: =COUNTIFS('Security Test Catalogue'!$A$2:$A$484,B38,'Security Test Catalogue'!$BA$2:$BA$484,"Critical") -> 1 | E38: =COUNTIFS('Security Test Catalogue'!$A$2:$A$484,B38,'Security Test Catalogue'!$BA$2:$BA$484,"High") -> 15 | F38: =COUNTIFS('Security Test Catalogue'!$A$2:$A$484,B38,'Security Test Catalogue'!$BD$2:$BD$484,"Ready") -> 0 | G38: =COUNTIFS('Security Test Catalogue'!$A$2:$A$484,B38,'Security Test Catalogue'!$BD$2:$BD$484,"Passed")+COUNTIFS('Security Test Catalogue'!$A$2:$A$484,B38,'Security Test Catalogue'!$BD$2:$BD$484,"Failed") -> 0 | H38: =COUNTIFS('Security Test Catalogue'!$A$2:$A$484,B38,'Security Test Catalogue'!$BD$2:$BD$484,"Failed") -> 0 | I38: =IFERROR(G38/C38,0) -> 0
B39: 5. Input, Parser & Query Safety | C39: =COUNTIF('Security Test Catalogue'!$A$2:$A$484,B39) -> 115 | D39: =COUNTIFS('Security Test Catalogue'!$A$2:$A$484,B39,'Security Test Catalogue'!$BA$2:$BA$484,"Critical") -> 0 | E39: =COUNTIFS('Security Test Catalogue'!$A$2:$A$484,B39,'Security Test Catalogue'!$BA$2:$BA$484,"High") -> 62 | F39: =COUNTIFS('Security Test Catalogue'!$A$2:$A$484,B39,'Security Test Catalogue'!$BD$2:$BD$484,"Ready") -> 0 | G39: =COUNTIFS('Security Test Catalogue'!$A$2:$A$484,B39,'Security Test Catalogue'!$BD$2:$BD$484,"Passed")+COUNTIFS('Security Test Catalogue'!$A$2:$A$484,B39,'Security Test Catalogue'!$BD$2:$BD$484,"Failed") -> 0 | H39: =COUNTIFS('Security Test Catalogue'!$A$2:$A$484,B39,'Security Test Catalogue'!$BD$2:$BD$484,"Failed") -> 0 | I39: =IFERROR(G39/C39,0) -> 0
B40: 6. Data Exposure, Privacy & Cryptography | C40: =COUNTIF('Security Test Catalogue'!$A$2:$A$484,B40) -> 21 | D40: =COUNTIFS('Security Test Catalogue'!$A$2:$A$484,B40,'Security Test Catalogue'!$BA$2:$BA$484,"Critical") -> 0 | E40: =COUNTIFS('Security Test Catalogue'!$A$2:$A$484,B40,'Security Test Catalogue'!$BA$2:$BA$484,"High") -> 18 | F40: =COUNTIFS('Security Test Catalogue'!$A$2:$A$484,B40,'Security Test Catalogue'!$BD$2:$BD$484,"Ready") -> 0 | G40: =COUNTIFS('Security Test Catalogue'!$A$2:$A$484,B40,'Security Test Catalogue'!$BD$2:$BD$484,"Passed")+COUNTIFS('Security Test Catalogue'!$A$2:$A$484,B40,'Security Test Catalogue'!$BD$2:$BD$484,"Failed") -> 0 | H40: =COUNTIFS('Security Test Catalogue'!$A$2:$A$484,B40,'Security Test Catalogue'!$BD$2:$BD$484,"Failed") -> 0 | I40: =IFERROR(G40/C40,0) -> 0
B41: 7. Guest, File & Public Surface Security | C41: =COUNTIF('Security Test Catalogue'!$A$2:$A$484,B41) -> 24 | D41: =COUNTIFS('Security Test Catalogue'!$A$2:$A$484,B41,'Security Test Catalogue'!$BA$2:$BA$484,"Critical") -> 0 | E41: =COUNTIFS('Security Test Catalogue'!$A$2:$A$484,B41,'Security Test Catalogue'!$BA$2:$BA$484,"High") -> 4 | F41: =COUNTIFS('Security Test Catalogue'!$A$2:$A$484,B41,'Security Test Catalogue'!$BD$2:$BD$484,"Ready") -> 0 | G41: =COUNTIFS('Security Test Catalogue'!$A$2:$A$484,B41,'Security Test Catalogue'!$BD$2:$BD$484,"Passed")+COUNTIFS('Security Test Catalogue'!$A$2:$A$484,B41,'Security Test Catalogue'!$BD$2:$BD$484,"Failed") -> 0 | H41: =COUNTIFS('Security Test Catalogue'!$A$2:$A$484,B41,'Security Test Catalogue'!$BD$2:$BD$484,"Failed") -> 0 | I41: =IFERROR(G41/C41,0) -> 0
B42: 8. Integration & Trust Boundary Security | C42: =COUNTIF('Security Test Catalogue'!$A$2:$A$484,B42) -> 47 | D42: =COUNTIFS('Security Test Catalogue'!$A$2:$A$484,B42,'Security Test Catalogue'!$BA$2:$BA$484,"Critical") -> 0 | E42: =COUNTIFS('Security Test Catalogue'!$A$2:$A$484,B42,'Security Test Catalogue'!$BA$2:$BA$484,"High") -> 7 | F42: =COUNTIFS('Security Test Catalogue'!$A$2:$A$484,B42,'Security Test Catalogue'!$BD$2:$BD$484,"Ready") -> 0 | G42: =COUNTIFS('Security Test Catalogue'!$A$2:$A$484,B42,'Security Test Catalogue'!$BD$2:$BD$484,"Passed")+COUNTIFS('Security Test Catalogue'!$A$2:$A$484,B42,'Security Test Catalogue'!$BD$2:$BD$484,"Failed") -> 0 | H42: =COUNTIFS('Security Test Catalogue'!$A$2:$A$484,B42,'Security Test Catalogue'!$BD$2:$BD$484,"Failed") -> 0 | I42: =IFERROR(G42/C42,0) -> 0
B43: 9. Abuse Resistance, Logging & Monitoring | C43: =COUNTIF('Security Test Catalogue'!$A$2:$A$484,B43) -> 15 | D43: =COUNTIFS('Security Test Catalogue'!$A$2:$A$484,B43,'Security Test Catalogue'!$BA$2:$BA$484,"Critical") -> 0 | E43: =COUNTIFS('Security Test Catalogue'!$A$2:$A$484,B43,'Security Test Catalogue'!$BA$2:$BA$484,"High") -> 0 | F43: =COUNTIFS('Security Test Catalogue'!$A$2:$A$484,B43,'Security Test Catalogue'!$BD$2:$BD$484,"Ready") -> 0 | G43: =COUNTIFS('Security Test Catalogue'!$A$2:$A$484,B43,'Security Test Catalogue'!$BD$2:$BD$484,"Passed")+COUNTIFS('Security Test Catalogue'!$A$2:$A$484,B43,'Security Test Catalogue'!$BD$2:$BD$484,"Failed") -> 0 | H43: =COUNTIFS('Security Test Catalogue'!$A$2:$A$484,B43,'Security Test Catalogue'!$BD$2:$BD$484,"Failed") -> 0 | I43: =IFERROR(G43/C43,0) -> 0
B44: 10. Business Logic & Transaction Integrity | C44: =COUNTIF('Security Test Catalogue'!$A$2:$A$484,B44) -> 20 | D44: =COUNTIFS('Security Test Catalogue'!$A$2:$A$484,B44,'Security Test Catalogue'!$BA$2:$BA$484,"Critical") -> 0 | E44: =COUNTIFS('Security Test Catalogue'!$A$2:$A$484,B44,'Security Test Catalogue'!$BA$2:$BA$484,"High") -> 20 | F44: =COUNTIFS('Security Test Catalogue'!$A$2:$A$484,B44,'Security Test Catalogue'!$BD$2:$BD$484,"Ready") -> 0 | G44: =COUNTIFS('Security Test Catalogue'!$A$2:$A$484,B44,'Security Test Catalogue'!$BD$2:$BD$484,"Passed")+COUNTIFS('Security Test Catalogue'!$A$2:$A$484,B44,'Security Test Catalogue'!$BD$2:$BD$484,"Failed") -> 0 | H44: =COUNTIFS('Security Test Catalogue'!$A$2:$A$484,B44,'Security Test Catalogue'!$BD$2:$BD$484,"Failed") -> 0 | I44: =IFERROR(G44/C44,0) -> 0
B45: 11. Configuration, Inventory & Engineering Assurance | C45: =COUNTIF('Security Test Catalogue'!$A$2:$A$484,B45) -> 64 | D45: =COUNTIFS('Security Test Catalogue'!$A$2:$A$484,B45,'Security Test Catalogue'!$BA$2:$BA$484,"Critical") -> 0 | E45: =COUNTIFS('Security Test Catalogue'!$A$2:$A$484,B45,'Security Test Catalogue'!$BA$2:$BA$484,"High") -> 8 | F45: =COUNTIFS('Security Test Catalogue'!$A$2:$A$484,B45,'Security Test Catalogue'!$BD$2:$BD$484,"Ready") -> 0 | G45: =COUNTIFS('Security Test Catalogue'!$A$2:$A$484,B45,'Security Test Catalogue'!$BD$2:$BD$484,"Passed")+COUNTIFS('Security Test Catalogue'!$A$2:$A$484,B45,'Security Test Catalogue'!$BD$2:$BD$484,"Failed") -> 0 | H45: =COUNTIFS('Security Test Catalogue'!$A$2:$A$484,B45,'Security Test Catalogue'!$BD$2:$BD$484,"Failed") -> 0 | I45: =IFERROR(G45/C45,0) -> 0
B46: 12. Client, Platform & General API Assurance | C46: =COUNTIF('Security Test Catalogue'!$A$2:$A$484,B46) -> 7 | D46: =COUNTIFS('Security Test Catalogue'!$A$2:$A$484,B46,'Security Test Catalogue'!$BA$2:$BA$484,"Critical") -> 0 | E46: =COUNTIFS('Security Test Catalogue'!$A$2:$A$484,B46,'Security Test Catalogue'!$BA$2:$BA$484,"High") -> 4 | F46: =COUNTIFS('Security Test Catalogue'!$A$2:$A$484,B46,'Security Test Catalogue'!$BD$2:$BD$484,"Ready") -> 0 | G46: =COUNTIFS('Security Test Catalogue'!$A$2:$A$484,B46,'Security Test Catalogue'!$BD$2:$BD$484,"Passed")+COUNTIFS('Security Test Catalogue'!$A$2:$A$484,B46,'Security Test Catalogue'!$BD$2:$BD$484,"Failed") -> 0 | H46: =COUNTIFS('Security Test Catalogue'!$A$2:$A$484,B46,'Security Test Catalogue'!$BD$2:$BD$484,"Failed") -> 0 | I46: =IFERROR(G46/C46,0) -> 0
B49: 3 MINIMUM EXECUTION EVIDENCE
B50: A test cannot be marked Passed or Failed until the following evidence is present and linked in the catalogue.
B52: Evidence class | C52: Minimum required content
B53: Context | C53: Environment, date, tester, exact route/component and version
B54: Identity | C54: Tested identity, role, entitlement and comparison role
B55: Procedure | C55: Baseline, negative variant, safety limits and cleanup performed
B56: Observation | C56: Expected result, actual result, status code/state and logs
B57: Traceability | C57: Request/response or artefact IDs, correlation ID and redactions
B58: Decision | C58: Pass/fail criteria, control observed and limitation statement
B59: Finding | C59: Impact, blast radius, severity rationale, owner and defect ID
B60: Retest | C60: Fixed version/configuration, repeated evidence and closure outcome
B62: Assurance principle: a test result is bounded by the executed route, role, method, data context, release and environment. Equivalent routes and roles require representative validation.
B64: 4 TEST DEPENDENCY AND EXECUTION ORDER
B65: Blocking prerequisites must be Ready, Passed or explicitly Waived before the dependent test is marked Ready. Companion tests are non-blocking and provide corroboration or alternate-path coverage.
B67: Wave 1 - Foundation | C67: Baseline identity, ownership, inventory, telemetry and primary control tests.
B68: Wave 2 - Control Variants | C68: Scenario variants that rely on a known baseline or entitlement model.
B69: Wave 3 - Dependent / Composite | C69: Composite, cross-boundary or multi-control tests with several prerequisites.
B70: Dependency Gate = Blocked | C70: Do not execute. Resolve missing prerequisite identity, data, route, evidence or baseline.
B71: Dependency Gate = Waived | C71: Document approver, reason, residual uncertainty and compensating evidence.

Sheet Control Taxonomy
B1: API SECURITY CONTROL TAXONOMY
B3: How the 483 tests are organised: Security Domain → Control Subcategory → Test IDs → Execution dependencies
B5: READING GUIDE • Security Domain is the parent security objective. Control Subcategory identifies the specific control capability being tested. Counts show catalogue concentration and inherent priority. Foundation tests establish baselines; dependent tests reuse identity, data or evidence and must satisfy their dependency gate before execution.
B8: PARENT DOMAINS | D8: CONTROL SUBCATEGORIES | G8: TOTAL TESTS | I8: CRITICAL + HIGH | L8: FOUNDATION TESTS
B9: 12 | D9: 32 | G9: 483 | I9: 267 | L9: 32
B11: Top-level security objectives | D11: Specific control capabilities | G11: Unique catalogue test cases | I11: Priority test coverage | L11: Baseline tests to run first
B13: 1 DOMAIN MAP
B14: Executive view of the 12 parent domains. Use this section to understand purpose, test concentration, priority and foundation coverage.
B16: Security Domain | C16: Security Objective | D16: Primary Review Focus | E16: Tests | F16: Critical | G16: High | H16: Medium | I16: Wave 1 | J16: Blocking Dependencies | K16: Subcategories | L16: Domain Code | M16: Representative Test IDs
B17: 1. Identity, Authentication & Session | C17: Establish trustworthy identity, credential, token and session handling before protected API use. | D17: Authentication strength, token context, MFA, session lifecycle, recovery and service identity. | E17: 79 | F17: 2 | G17: 74 | H17: 3 | I17: 5 | J17: 74 | K17: 5 | L17: IAM | M17: API-IAM-001, API-IAM-002, API-IAM-003, API-IAM-004, API-IAM-005, API-IAM-006 …
B18: 2. Record & Tenant Access (BOLA / IDOR) | C18: Ensure every record-bearing operation enforces object ownership, tenant and entitlement boundaries. | D18: Cross-user IDs, cross-tenant access, nested relationships, search leakage, batch and composite access. | E18: 22 | F18: 9 | G18: 11 | H18: 2 | I18: 1 | J18: 22 | K18: 1 | L18: BOLA | M18: API-BOLA-001, API-BOLA-002, API-BOLA-003, API-BOLA-004, API-BOLA-005, API-BOLA-006 …
B19: 3. Privilege & Function Boundaries (BFLA) | C19: Prevent lower-privilege identities from invoking protected functions or administrative actions. | D19: Role comparison, direct backend invocation, workflow privilege, alternate verbs and hidden routes. | E19: 35 | F19: 5 | G19: 27 | H19: 3 | I19: 3 | J19: 35 | K19: 3 | L19: BFLA | M19: API-BFLA-001, API-BFLA-002, API-BFLA-003, API-BFLA-004, API-BFLA-005, API-BFLA-006 …
B20: 4. Field, Property & Payload Authorisation | C20: Restrict fields and properties that may be read, created, updated, filtered or inferred. | D20: Field access, mass assignment, over-posting, projection, nested properties and inference. | E20: 34 | F20: 1 | G20: 15 | H20: 18 | I20: 2 | J20: 32 | K20: 2 | L20: PROP | M20: API-PROP-001, API-PROP-002, API-PROP-003, API-PROP-004, API-PROP-005, API-PROP-006 …
B21: 5. Input, Parser & Query Safety | C21: Keep untrusted input from changing query scope, parser meaning, execution flow or service stability. | D21: Injection, content types, duplicate parameters, boundaries, deserialisation, encoding and memory safety. | E21: 115 | F21: 0 | G21: 62 | H21: 53 | I21: 2 | J21: 114 | K21: 2 | L21: INPUT | M21: API-INPUT-001, API-INPUT-002, API-INPUT-003, API-INPUT-004, API-INPUT-005, API-INPUT-006 …
B22: 6. Data Exposure, Privacy & Cryptography | C22: Minimise exposed data and protect sensitive information, secrets and cryptographic material. | D22: Response minimisation, secrets, encryption, caching, metadata, pagination and privacy. | E22: 21 | F22: 0 | G22: 18 | H22: 3 | I22: 2 | J22: 20 | K22: 2 | L22: DATA | M22: API-DATA-001, API-DATA-002, API-DATA-003, API-DATA-004, API-DATA-005, API-DATA-006 …
B23: 7. Guest, File & Public Surface Security | C23: Ensure anonymous users and public delivery paths expose only explicitly public content. | D23: Guest APIs, file access, uploads, public links, recovery surfaces, archives and paths. | E23: 24 | F23: 0 | G23: 4 | H23: 20 | I23: 1 | J23: 23 | K23: 1 | L23: PUBLIC | M23: API-PUBLIC-001, API-PUBLIC-002, API-PUBLIC-003, API-PUBLIC-004, API-PUBLIC-005, API-PUBLIC-006 …
B24: 8. Integration & Trust Boundary Security | C24: Constrain trust across middleware, webhooks, service identities and downstream APIs. | D24: SSRF, callbacks, delegated credentials, downstream authorisation, transport integrity and third parties. | E24: 47 | F24: 0 | G24: 7 | H24: 40 | I24: 4 | J24: 47 | K24: 4 | L24: TRUST | M24: API-TRUST-001, API-TRUST-002, API-TRUST-003, API-TRUST-004, API-TRUST-005, API-TRUST-006 …
B25: 9. Abuse Resistance, Logging & Monitoring | C25: Detect and constrain automated abuse, excessive consumption and suspicious access patterns. | D25: Rate limits, quotas, scraping, bulk extraction, logging, correlation, alerting and recovery. | E25: 15 | F25: 0 | G25: 0 | H25: 15 | I25: 2 | J25: 15 | K25: 2 | L25: MON | M25: API-MON-001, API-MON-002, API-MON-003, API-MON-004, API-MON-005, API-MON-006 …
B26: 10. Business Logic & Transaction Integrity | C26: Preserve valid process sequence, state, uniqueness, concurrency and transaction outcomes. | D26: Workflow state, prerequisites, replay, idempotency, race conditions and transaction integrity. | E26: 20 | F26: 0 | G26: 20 | H26: 0 | I26: 4 | J26: 20 | K26: 4 | L26: LOGIC | M26: API-LOGIC-001, API-LOGIC-002, API-LOGIC-003, API-LOGIC-004, API-LOGIC-005, API-LOGIC-006 …
B27: 11. Configuration, Inventory & Engineering Assurance | C27: Maintain secure ownership, configuration, implementation and lifecycle governance for APIs. | D27: Inventory, baselines, code/design, dependencies, deployment, retirement, permissions and training. | E27: 64 | F27: 0 | G27: 8 | H27: 56 | I27: 1 | J27: 64 | K27: 1 | L27: HARD | M27: API-HARD-001, API-HARD-002, API-HARD-003, API-HARD-004, API-HARD-005, API-HARD-006 …
B28: 12. Client, Platform & General API Assurance | C28: Protect browser-facing and platform-level API behaviour outside the core server control domains. | D28: CORS, browser headers, client storage, rendering, protocol contracts and platform exposure. | E28: 7 | F28: 0 | G28: 4 | H28: 3 | I28: 5 | J28: 3 | K28: 5 | L28: PLATFORM | M28: API-PLATFORM-001, API-PLATFORM-002, API-PLATFORM-003, API-PLATFORM-004, API-PLATFORM-005, API-PLATFORM-006 …
B31: 2 DETAILED CONTROL TAXONOMY
B32: Each row is a specific control capability. The description explains what it protects; the metrics show risk concentration, execution style and dependency profile.
A34: Security Domain | B34: Control Subcategory | C34: Control Intent / What It Protects | D34: Tests | E34: Critical | F34: High | G34: Medium | H34: Dynamic | I34: Hybrid | J34: Review | K34: Wave 1 | L34: Blocking | M34: Companion | N34: Representative Test IDs
A35: 1. Identity, Authentication & Session
A36: 1. Identity, Authentication & Session | B36: API Keys & Client Credentials | C36: Validate issuance, scope, storage, rotation, revocation and least privilege for non-user credentials. | D36: 3 | E36: 1 | F36: 2 | G36: 0 | H36: 2 | I36: 1 | J36: 0 | K36: 1 | L36: 2 | M36: 2 | N36: API-IAM-001, API-IAM-003, API-IAM-043
A37: 1. Identity, Authentication & Session | B37: MFA & Step-up Authentication | C37: Verify additional assurance is required and retained for sensitive actions. | D37: 1 | E37: 0 | F37: 1 | G37: 0 | H37: 0 | I37: 1 | J37: 0 | K37: 1 | L37: 0 | M37: 0 | N37: API-IAM-070
A38: 1. Identity, Authentication & Session | B38: Password & Account Recovery | C38: Prevent enumeration, weak reset tokens, recovery bypass and credential abuse. | D38: 2 | E38: 0 | F38: 2 | G38: 0 | H38: 0 | I38: 2 | J38: 0 | K38: 1 | L38: 1 | M38: 2 | N38: API-IAM-027, API-IAM-075
A39: 1. Identity, Authentication & Session | B39: Session Lifecycle & Cookies | C39: Protect session creation, rotation, timeout, logout, replay and browser cookie state. | D39: 21 | E39: 0 | F39: 21 | G39: 0 | H39: 0 | I39: 21 | J39: 0 | K39: 1 | L39: 20 | M39: 2 | N39: API-IAM-007, API-IAM-008, API-IAM-011, API-IAM-012, API-IAM-015, API-IAM-018, API-IAM-023, API-IAM-026, API-IAM-029, API-IAM-034 …
A40: 1. Identity, Authentication & Session | B40: Token Validation & JWT | C40: Validate signature, algorithm, issuer, audience, scope, lifetime, key selection and replay context. | D40: 52 | E40: 1 | F40: 48 | G40: 3 | H40: 20 | I40: 30 | J40: 2 | K40: 1 | L40: 51 | M40: 27 | N40: API-IAM-002, API-IAM-004, API-IAM-005, API-IAM-006, API-IAM-009, API-IAM-010, API-IAM-013, API-IAM-014, API-IAM-016, API-IAM-017 …
A41: Domain total | B41: 1. Identity, Authentication & Session | D41: 79 | E41: 2 | F41: 74 | G41: 3 | H41: 22 | I41: 55 | J41: 2 | K41: 5 | L41: 74 | M41: 33
A43: 2. Record & Tenant Access (BOLA / IDOR)
A44: 2. Record & Tenant Access (BOLA / IDOR) | B44: Object Identifier Authorisation | C44: Ensure knowledge or substitution of an identifier never grants access. | D44: 22 | E44: 9 | F44: 11 | G44: 2 | H44: 12 | I44: 10 | J44: 0 | K44: 1 | L44: 22 | M44: 14 | N44: API-BOLA-001, API-BOLA-002, API-BOLA-003, API-BOLA-004, API-BOLA-005, API-BOLA-006, API-BOLA-007, API-BOLA-008, API-BOLA-009, API-BOLA-010 …
A45: Domain total | B45: 2. Record & Tenant Access (BOLA / IDOR) | D45: 22 | E45: 9 | F45: 11 | G45: 2 | H45: 12 | I45: 10 | J45: 0 | K45: 1 | L45: 22 | M45: 14
A47: 3. Privilege & Function Boundaries (BFLA)
A48: 3. Privilege & Function Boundaries (BFLA) | B48: Administrative Function Access | C48: Restrict configuration and administrative actions to explicitly authorised roles. | D48: 7 | E48: 3 | F48: 3 | G48: 1 | H48: 3 | I48: 3 | J48: 1 | K48: 1 | L48: 7 | M48: 2 | N48: API-BFLA-001, API-BFLA-002, API-BFLA-005, API-BFLA-019, API-BFLA-023, API-BFLA-026, API-BFLA-033
A49: 3. Privilege & Function Boundaries (BFLA) | B49: Function-level Authorisation | C49: Prevent direct invocation of functions hidden or unavailable in the intended client. | D49: 22 | E49: 2 | F49: 19 | G49: 1 | H49: 8 | I49: 14 | J49: 0 | K49: 1 | L49: 22 | M49: 22 | N49: API-BFLA-003, API-BFLA-004, API-BFLA-006, API-BFLA-008, API-BFLA-009, API-BFLA-010, API-BFLA-011, API-BFLA-012, API-BFLA-013, API-BFLA-014 …
A50: 3. Privilege & Function Boundaries (BFLA) | B50: Role & Permission Enforcement | C50: Re-check role, scope and permission on the server for every protected operation. | D50: 6 | E50: 0 | F50: 5 | G50: 1 | H50: 1 | I50: 3 | J50: 2 | K50: 1 | L50: 6 | M50: 6 | N50: API-BFLA-007, API-BFLA-021, API-BFLA-022, API-BFLA-025, API-BFLA-027, API-BFLA-034
A51: Domain total | B51: 3. Privilege & Function Boundaries (BFLA) | D51: 35 | E51: 5 | F51: 27 | G51: 3 | H51: 12 | I51: 20 | J51: 3 | K51: 3 | L51: 35 | M51: 30
A53: 4. Field, Property & Payload Authorisation
A54: 4. Field, Property & Payload Authorisation | B54: Field-level Read Controls | C54: Exclude restricted fields, derived metadata and hidden nested properties. | D54: 33 | E54: 1 | F54: 14 | G54: 18 | H54: 12 | I54: 21 | J54: 0 | K54: 1 | L54: 32 | M54: 33 | N54: API-PROP-001, API-PROP-002, API-PROP-003, API-PROP-004, API-PROP-005, API-PROP-006, API-PROP-007, API-PROP-008, API-PROP-009, API-PROP-010 …
A55: 4. Field, Property & Payload Authorisation | B55: Mass Assignment & Overposting | C55: Allow only explicitly approved fields on create and update. | D55: 1 | E55: 0 | F55: 1 | G55: 0 | H55: 0 | I55: 1 | J55: 0 | K55: 1 | L55: 0 | M55: 1 | N55: API-PROP-015
A56: Domain total | B56: 4. Field, Property & Payload Authorisation | D56: 34 | E56: 1 | F56: 15 | G56: 18 | H56: 12 | I56: 22 | J56: 0 | K56: 2 | L56: 32 | M56: 34
A58: 5. Input, Parser & Query Safety
A59: 5. Input, Parser & Query Safety | B59: Injection Resistance | C59: Bind or safely encode untrusted input so it cannot alter execution or query meaning. | D59: 7 | E59: 0 | F59: 1 | G59: 6 | H59: 0 | I59: 7 | J59: 0 | K59: 1 | L59: 6 | M59: 7 | N59: API-INPUT-056, API-INPUT-084, API-INPUT-085, API-INPUT-086, API-INPUT-091, API-INPUT-097, API-INPUT-098
A60: 5. Input, Parser & Query Safety | B60: Parser & Content-type Safety | C60: Reject ambiguous, unsupported or dangerous parser and content-type behaviours. | D60: 108 | E60: 0 | F60: 61 | G60: 47 | H60: 47 | I60: 48 | J60: 13 | K60: 1 | L60: 108 | M60: 108 | N60: API-INPUT-001, API-INPUT-002, API-INPUT-003, API-INPUT-004, API-INPUT-005, API-INPUT-006, API-INPUT-007, API-INPUT-008, API-INPUT-009, API-INPUT-010 …
A61: Domain total | B61: 5. Input, Parser & Query Safety | D61: 115 | E61: 0 | F61: 62 | G61: 53 | H61: 47 | I61: 55 | J61: 13 | K61: 2 | L61: 114 | M61: 115
A63: 6. Data Exposure, Privacy & Cryptography
A64: 6. Data Exposure, Privacy & Cryptography | B64: Cryptographic Key & Secret Management | C64: Protect cryptographic material throughout generation, storage, use, rotation and retirement. | D64: 17 | E64: 0 | F64: 15 | G64: 2 | H64: 0 | I64: 2 | J64: 15 | K64: 1 | L64: 16 | M64: 17 | N64: API-DATA-001, API-DATA-002, API-DATA-003, API-DATA-004, API-DATA-005, API-DATA-006, API-DATA-007, API-DATA-009, API-DATA-010, API-DATA-011 …
A65: 6. Data Exposure, Privacy & Cryptography | B65: Sensitive Data Minimisation | C65: Return only the data required for the authorised business purpose. | D65: 4 | E65: 0 | F65: 3 | G65: 1 | H65: 0 | I65: 3 | J65: 1 | K65: 1 | L65: 4 | M65: 4 | N65: API-DATA-008, API-DATA-016, API-DATA-017, API-DATA-021
A66: Domain total | B66: 6. Data Exposure, Privacy & Cryptography | D66: 21 | E66: 0 | F66: 18 | G66: 3 | H66: 0 | I66: 5 | J66: 16 | K66: 2 | L66: 20 | M66: 21
A68: 7. Guest, File & Public Surface Security
A69: 7. Guest, File & Public Surface Security | B69: Guest & Anonymous API Access | C69: Deny protected data and actions to unauthenticated or public contexts. | D69: 24 | E69: 0 | F69: 4 | G69: 20 | H69: 0 | I69: 23 | J69: 1 | K69: 1 | L69: 23 | M69: 24 | N69: API-PUBLIC-001, API-PUBLIC-002, API-PUBLIC-003, API-PUBLIC-004, API-PUBLIC-005, API-PUBLIC-006, API-PUBLIC-007, API-PUBLIC-008, API-PUBLIC-009, API-PUBLIC-010 …
A70: Domain total | B70: 7. Guest, File & Public Surface Security | D70: 24 | E70: 0 | F70: 4 | G70: 20 | H70: 0 | I70: 23 | J70: 1 | K70: 1 | L70: 23 | M70: 24
A72: 8. Integration & Trust Boundary Security
A73: 8. Integration & Trust Boundary Security | B73: Downstream Authorisation | C73: Require the receiving service to re-evaluate user and business entitlement. | D73: 2 | E73: 0 | F73: 1 | G73: 1 | H73: 0 | I73: 2 | J73: 0 | K73: 1 | L73: 2 | M73: 2 | N73: API-TRUST-004, API-TRUST-039
A74: 8. Integration & Trust Boundary Security | B74: Integration Trust Boundary Enforcement | C74: Authenticate, scope and trace trust across every service boundary. | D74: 18 | E74: 0 | F74: 4 | G74: 14 | H74: 0 | I74: 7 | J74: 11 | K74: 1 | L74: 18 | M74: 18 | N74: API-TRUST-001, API-TRUST-002, API-TRUST-005, API-TRUST-006, API-TRUST-009, API-TRUST-012, API-TRUST-013, API-TRUST-020, API-TRUST-022, API-TRUST-023 …
A75: 8. Integration & Trust Boundary Security | B75: Outbound Request & SSRF Controls | C75: Constrain destinations, paths, protocols and redirects using server-side policy. | D75: 26 | E75: 0 | F75: 1 | G75: 25 | H75: 0 | I75: 1 | J75: 25 | K75: 1 | L75: 26 | M75: 26 | N75: API-TRUST-007, API-TRUST-008, API-TRUST-010, API-TRUST-011, API-TRUST-014, API-TRUST-015, API-TRUST-016, API-TRUST-017, API-TRUST-018, API-TRUST-019 …
A76: 8. Integration & Trust Boundary Security | B76: Webhook & Callback Authenticity | C76: Validate signature, freshness, source and replay protection for inbound events. | D76: 1 | E76: 0 | F76: 1 | G76: 0 | H76: 0 | I76: 1 | J76: 0 | K76: 1 | L76: 1 | M76: 1 | N76: API-TRUST-003
A77: Domain total | B77: 8. Integration & Trust Boundary Security | D77: 47 | E77: 0 | F77: 7 | G77: 40 | H77: 0 | I77: 11 | J77: 36 | K77: 4 | L77: 47 | M77: 47
A79: 9. Abuse Resistance, Logging & Monitoring
A80: 9. Abuse Resistance, Logging & Monitoring | B80: Rate Limiting & Quotas | C80: Apply safe request, cost and concurrency limits before harmful consumption. | D80: 2 | E80: 0 | F80: 0 | G80: 2 | H80: 0 | I80: 1 | J80: 1 | K80: 1 | L80: 2 | M80: 2 | N80: API-MON-005, API-MON-012
A81: 9. Abuse Resistance, Logging & Monitoring | B81: Security Logging & Correlation | C81: Record attributable security events and preserve end-to-end traceability. | D81: 13 | E81: 0 | F81: 0 | G81: 13 | H81: 0 | I81: 13 | J81: 0 | K81: 1 | L81: 13 | M81: 13 | N81: API-MON-001, API-MON-002, API-MON-003, API-MON-004, API-MON-006, API-MON-007, API-MON-008, API-MON-009, API-MON-010, API-MON-011 …
A82: Domain total | B82: 9. Abuse Resistance, Logging & Monitoring | D82: 15 | E82: 0 | F82: 0 | G82: 15 | H82: 0 | I82: 14 | J82: 1 | K82: 2 | L82: 15 | M82: 15
A84: 10. Business Logic & Transaction Integrity
A85: 10. Business Logic & Transaction Integrity | B85: Concurrency & Race Conditions | C85: Preserve consistent outcomes when actions overlap in time. | D85: 1 | E85: 0 | F85: 1 | G85: 0 | H85: 1 | I85: 0 | J85: 0 | K85: 1 | L85: 1 | M85: 1 | N85: API-LOGIC-012
A86: 10. Business Logic & Transaction Integrity | B86: Replay & Idempotency | C86: Prevent repeated requests from creating unintended repeated effects. | D86: 3 | E86: 0 | F86: 3 | G86: 0 | H86: 2 | I86: 1 | J86: 0 | K86: 1 | L86: 3 | M86: 3 | N86: API-LOGIC-004, API-LOGIC-006, API-LOGIC-014
A87: 10. Business Logic & Transaction Integrity | B87: Transaction Integrity | C87: Keep multi-step operations atomic, consistent and authorised. | D87: 11 | E87: 0 | F87: 11 | G87: 0 | H87: 10 | I87: 1 | J87: 0 | K87: 1 | L87: 11 | M87: 11 | N87: API-LOGIC-001, API-LOGIC-002, API-LOGIC-003, API-LOGIC-005, API-LOGIC-008, API-LOGIC-009, API-LOGIC-010, API-LOGIC-011, API-LOGIC-013, API-LOGIC-016 …
A88: 10. Business Logic & Transaction Integrity | B88: Workflow State Enforcement | C88: Permit only valid state transitions for the role and current record state. | D88: 5 | E88: 0 | F88: 5 | G88: 0 | H88: 2 | I88: 3 | J88: 0 | K88: 1 | L88: 5 | M88: 5 | N88: API-LOGIC-007, API-LOGIC-015, API-LOGIC-017, API-LOGIC-018, API-LOGIC-020
A89: Domain total | B89: 10. Business Logic & Transaction Integrity | D89: 20 | E89: 0 | F89: 20 | G89: 0 | H89: 15 | I89: 5 | J89: 0 | K89: 4 | L89: 20 | M89: 20
A91: 11. Configuration, Inventory & Engineering Assurance
A92: 11. Configuration, Inventory & Engineering Assurance | B92: API Inventory & Ownership | C92: Maintain authoritative inventory, ownership, exposure, version and lifecycle state. | D92: 64 | E92: 0 | F92: 8 | G92: 56 | H92: 15 | I92: 10 | J92: 39 | K92: 1 | L92: 64 | M92: 24 | N92: API-HARD-001, API-HARD-002, API-HARD-003, API-HARD-004, API-HARD-005, API-HARD-006, API-HARD-007, API-HARD-008, API-HARD-009, API-HARD-010 …
A93: Domain total | B93: 11. Configuration, Inventory & Engineering Assurance | D93: 64 | E93: 0 | F93: 8 | G93: 56 | H93: 15 | I93: 10 | J93: 39 | K93: 1 | L93: 64 | M93: 24
A95: 12. Client, Platform & General API Assurance
A96: 12. Client, Platform & General API Assurance | B96: Browser Origin & CORS Controls | C96: Permit browser cross-origin access only from approved origins and methods. | D96: 1 | E96: 0 | F96: 1 | G96: 0 | H96: 0 | I96: 1 | J96: 0 | K96: 1 | L96: 0 | M96: 0 | N96: API-PLATFORM-001
A97: 12. Client, Platform & General API Assurance | B97: Browser Security Headers | C97: Use restrictive browser security headers on sensitive routes. | D97: 2 | E97: 0 | F97: 0 | G97: 2 | H97: 0 | I97: 2 | J97: 0 | K97: 1 | L97: 1 | M97: 0 | N97: API-PLATFORM-005, API-PLATFORM-006
A98: 12. Client, Platform & General API Assurance | B98: Client Rendering & Script Safety | C98: Encode or sanitise untrusted content rendered by the client. | D98: 1 | E98: 0 | F98: 1 | G98: 0 | H98: 0 | I98: 1 | J98: 0 | K98: 1 | L98: 0 | M98: 1 | N98: API-PLATFORM-003
A99: 12. Client, Platform & General API Assurance | B99: Client-side Storage & Bootstrap Data | C99: Validate the 'Client-side Storage & Bootstrap Data' control family for the scoped API surface and its relevant roles, data and trust boundaries. | D99: 2 | E99: 0 | F99: 1 | G99: 1 | H99: 0 | I99: 2 | J99: 0 | K99: 1 | L99: 1 | M99: 2 | N99: API-PLATFORM-004, API-PLATFORM-007
A100: 12. Client, Platform & General API Assurance | B100: Platform Surface Exposure | C100: Validate the 'Platform Surface Exposure' control family for the scoped API surface and its relevant roles, data and trust boundaries. | D100: 1 | E100: 0 | F100: 1 | G100: 0 | H100: 0 | I100: 1 | J100: 0 | K100: 1 | L100: 1 | M100: 1 | N100: API-PLATFORM-002
A101: Domain total | B101: 12. Client, Platform & General API Assurance | D101: 7 | E101: 0 | F101: 4 | G101: 3 | H101: 0 | I101: 7 | J101: 0 | K101: 5 | L101: 3 | M101: 4
B103: 3 HOW TO USE THE TAXONOMY
B104: This sheet is descriptive and planning-oriented. Test execution, evidence, dependencies and results remain authoritative in the Security Test Catalogue and Test Dependency Map.
B106: Security Domain | C106: Parent security objective used for governance, reporting and assurance coverage.
B107: Control Subcategory | C107: Specific control capability under the parent domain. Filter here to identify exactly what is being tested.
B108: Control Intent | C108: Plain-English explanation of the protection the control is expected to provide.
B109: Critical / High / Medium | C109: Inherent catalogue priority. Re-rate only after real exposure, reachability, data sensitivity and blast radius are known.
B110: Wave 1 | C110: Foundation tests that should establish identity, ownership, entitlement, telemetry or core control baselines.
B111: Blocking | C111: Tests in the subcategory that require prerequisite Test IDs or equivalent approved evidence before becoming Ready.
B112: Companion | C112: Tests with non-blocking related controls that broaden assurance, alternate-path coverage or corroboration.
B113: Representative Test IDs | C113: Examples only. Use filters in Security Test Catalogue for the complete list and execution details.

Sheet Test Dependency Map
A1: Dependent Test ID | B1: Required / Related Test ID | C1: Relationship | D1: Blocking | E1: Invalidates Result if Failed | F1: Reusable Evidence Set ID | G1: Reusable Test Data Set ID | H1: Parallel Execution Group | I1: Recommended Wave | J1: Dependency Gate | K1: Waiver Reference | L1: Rationale
A2: API-IAM-001 | B2: API-BFLA-001 | C2: Companion / corroborating control | D2: No | E2: No | F2: EVD-IAM-API-KEYS-CLIENT-BASE | G2: TDATA-IAM-API-KEYS-CLIENT-BASE | H2: PAR-W1-IAM | I2: Wave 1 - Foundation | J2: Not Required | K2: Not waived | L2: Use configuration baseline as corroborating evidence where available.
A3: API-IAM-002 | B3: API-BFLA-001 | C3: Companion / corroborating control | D3: No | E3: No | F3: EVD-IAM-TOKEN-VALIDATION-BASE | G3: TDATA-IAM-TOKEN-VALIDATION-BASE | H3: PAR-W1-IAM | I3: Wave 1 - Foundation | J3: Not Required | K3: Not waived | L3: Use configuration baseline as corroborating evidence where available.
A4: API-IAM-003 | B4: API-IAM-001 | C4: Blocking prerequisite | D4: Yes | E4: Yes | F4: EVD-IAM-API-KEYS-CLIENT-BASE | G4: TDATA-IAM-API-KEYS-CLIENT-BASE | H4: PAR-W2-IAM | I4: Wave 2 - Control Variants | J4: Not Assessed | K4: Not waived | L4: Establish the baseline control behaviour for 'API Keys & Client Credentials' before testing this variant. Use configuration baseline as corroborating evidence where available.
A5: API-IAM-003 | B5: API-BFLA-001 | C5: Companion / corroborating control | D5: No | E5: No | F5: EVD-IAM-API-KEYS-CLIENT-BASE | G5: TDATA-IAM-API-KEYS-CLIENT-BASE | H5: PAR-W2-IAM | I5: Wave 2 - Control Variants | J5: Not Assessed | K5: Not waived | L5: Establish the baseline control behaviour for 'API Keys & Client Credentials' before testing this variant. Use configuration baseline as corroborating evidence where available.
A6: API-IAM-004 | B6: API-IAM-002 | C6: Blocking prerequisite | D6: Yes | E6: Yes | F6: EVD-IAM-TOKEN-VALIDATION-BASE | G6: TDATA-IAM-TOKEN-VALIDATION-BASE | H6: PAR-W2-IAM | I6: Wave 2 - Control Variants | J6: Not Assessed | K6: Not waived | L6: Establish the baseline control behaviour for 'Token Validation & JWT' before testing this variant. Confirm telemetry and correlation are available before abuse-pattern testing. Use the approved baseline threshold and stop-condition model. Use configuration baseline as corroborating evidence where available.
A7: API-IAM-004 | B7: API-BFLA-015 | C7: Blocking prerequisite | D7: Yes | E7: Yes | F7: EVD-IAM-TOKEN-VALIDATION-BASE | G7: TDATA-IAM-TOKEN-VALIDATION-BASE | H7: PAR-W2-IAM | I7: Wave 2 - Control Variants | J7: Not Assessed | K7: Not waived | L7: Establish the baseline control behaviour for 'Token Validation & JWT' before testing this variant. Confirm telemetry and correlation are available before abuse-pattern testing. Use the approved baseline threshold and stop-condition model. Use configuration baseline as corroborating evidence where available.
A8: API-IAM-004 | B8: API-IAM-016 | C8: Companion / corroborating control | D8: No | E8: No | F8: EVD-IAM-TOKEN-VALIDATION-BASE | G8: TDATA-IAM-TOKEN-VALIDATION-BASE | H8: PAR-W2-IAM | I8: Wave 2 - Control Variants | J8: Not Assessed | K8: Not waived | L8: Establish the baseline control behaviour for 'Token Validation & JWT' before testing this variant. Confirm telemetry and correlation are available before abuse-pattern testing. Use the approved baseline threshold and stop-condition model. Use configuration baseline as corroborating evidence where available.
A9: API-IAM-004 | B9: API-BFLA-001 | C9: Companion / corroborating control | D9: No | E9: No | F9: EVD-IAM-TOKEN-VALIDATION-BASE | G9: TDATA-IAM-TOKEN-VALIDATION-BASE | H9: PAR-W2-IAM | I9: Wave 2 - Control Variants | J9: Not Assessed | K9: Not waived | L9: Establish the baseline control behaviour for 'Token Validation & JWT' before testing this variant. Confirm telemetry and correlation are available before abuse-pattern testing. Use the approved baseline threshold and stop-condition model. Use configuration baseline as corroborating evidence where available.
A10: API-IAM-005 | B10: API-IAM-002 | C10: Blocking prerequisite | D10: Yes | E10: Yes | F10: EVD-IAM-TOKEN-VALIDATION-BASE | G10: TDATA-IAM-TOKEN-VALIDATION-BASE | H10: PAR-W2-IAM | I10: Wave 2 - Control Variants | J10: Not Assessed | K10: Not waived | L10: Establish the baseline control behaviour for 'Token Validation & JWT' before testing this variant. Use configuration baseline as corroborating evidence where available.
A11: API-IAM-005 | B11: API-BFLA-001 | C11: Companion / corroborating control | D11: No | E11: No | F11: EVD-IAM-TOKEN-VALIDATION-BASE | G11: TDATA-IAM-TOKEN-VALIDATION-BASE | H11: PAR-W2-IAM | I11: Wave 2 - Control Variants | J11: Not Assessed | K11: Not waived | L11: Establish the baseline control behaviour for 'Token Validation & JWT' before testing this variant. Use configuration baseline as corroborating evidence where available.
A12: API-IAM-006 | B12: API-IAM-002 | C12: Blocking prerequisite | D12: Yes | E12: Yes | F12: EVD-IAM-TOKEN-VALIDATION-BASE | G12: TDATA-IAM-TOKEN-VALIDATION-BASE | H12: PAR-W2-IAM | I12: Wave 2 - Control Variants | J12: Not Assessed | K12: Not waived | L12: Establish the baseline control behaviour for 'Token Validation & JWT' before testing this variant.
... A1446: API-PLATFORM-007 | B1446: API-PROP-001 | C1446: Companion / corroborating control | D1446: No | E1446: No | F1446: EVD-PLATFORM-CLIENT-SIDE-STOR-BASE | G1446: TDATA-PLATFORM-CLIENT-SIDE-STOR-BASE | H1446: PAR-W2-PLATFORM | I1446: Wave 2 - Control Variants | J1446: Not Assessed | K1446: Not waived | L1446: Establish the baseline control behaviour for 'Client-side Storage & Bootstrap Data' before testing this variant. Establish valid baseline parsing and input constraints. Establish the minimum authorised response and field-visibility baseline.

Sheet Execution Governance
A1: Section | B1: Rule | C1: Minimum evidence / action
A2: State progression | B2: Candidate → Applicable | C2: Applicability Decision and Applicability Rationale completed; scope owner reviewed.
A3: State progression | B3: Applicable → Ready | C3: Preconditions satisfied; target, environment, identities, data, safety, evidence capture and ownership available; Dependency Gate is Ready, Not Required or approved Waived.
A4: State progression | B4: Ready → In Progress | C4: Authorisation active; tester and date recorded; operational contact notified where required.
A5: State progression | B5: In Progress → Passed | C5: Pass criteria met; evidence linked; control observed recorded; no blocking prerequisite failed; limitations documented.
A6: State progression | B6: In Progress → Failed | C6: Failure criteria reproduced; impact and scope recorded; evidence linked; remediation owner and defect process initiated.
A7: State progression | B7: In Progress → Blocked | C7: Baseline, identity, data, target, telemetry, safety approval or prerequisite prevented a valid conclusion. Blocked is never Passed.
A8: Dependency | B8: Blocking prerequisite | C8: Must be Ready or Passed, or satisfied by approved equivalent evidence, before the dependent test is Ready.
A9: Dependency | B9: Non-blocking companion | C9: May remain outstanding; note bounded assurance and execute for corroboration or alternate-path coverage.
A10: Dependency | B10: Evidence/data reuse | C10: Reference the reusable set ID. Do not duplicate or silently modify shared baselines.
A11: Parallel execution | B11: Allowed | C11: No blocking relationship; no shared mutable record/configuration; no single-use credential; no combined traffic distortion; evidence remains independently traceable.
A12: Parallel execution | B12: Not allowed | C12: One test creates another baseline; both modify same state; one revokes identity/configuration; shared quota would distort results.
... A14: Retest | B14: Wave 4 | C14: Retest defect, then regress dependants listed in Invalidated By Failed Test IDs and related companions.

Sheet Security Test Catalogue
A1: Security Domain | B1: Control Subcategory | C1: Test ID | D1: Verification Type | E1: Feature / Surface | F1: Control / Test Scenario | G1: Test Objective | H1: Applicability & Scope | I1: Applicability Decision | J1: Applicability Rationale | K1: Preconditions / Required Test State | L1: Dependency Type | M1: Prerequisite Test IDs | N1: Companion / Related Test IDs | O1: Dependency Rationale | P1: Dependency Gate | Q1: Recommended Execution Wave | R1: Reusable Evidence Set ID | S1: Reusable Test Data Set ID | T1: Invalidated By Failed Test IDs | U1: Parallel Execution Group | V1: Dependency Waiver Reference | W1: Dependency Waiver Rationale | X1: Required Test Identities | Y1: Required Test Data | Z1: Environment | AA1: Ownership Classification | AB1: Logic Controlled By | AC1: Data Exposure Controlled By | AD1: Behaviour Changed By | AE1: User Context | AF1: Role Tested | AG1: Endpoint / Component | AH1: Method / Review Mode | AI1: Attacker Misuse Path | AJ1: Record Access Check | AK1: Privilege Boundary Check | AL1: Input Handling Check | AM1: Data Exposure Check | AN1: Public Access Check | AO1: Safe Validation Procedure | AP1: Safety / Stop Conditions | AQ1: Cleanup / Rollback | AR1: Expected Protected Behaviour | AS1: Pass / Fail Criteria | AT1: Failure Indicates | AU1: Denial / Pass Suggests | AV1: Next Defensive Check | AW1: Business Impact | AX1: OWASP API Security 2023 | AY1: OWASP Top 10 2025 | AZ1: NIST SP 800-53 Rev. 5 | BA1: Severity | BB1: Risk Score | BC1: Execution Priority | BD1: Status | BE1: Execution Date | BF1: Tester | BG1: Actual Result / Finding | BH1: Evidence Required | BI1: Evidence References | BJ1: Control Observed | BK1: Remediation Owner | BL1: Defect ID | BM1: Retest Result | BN1: Notes | BO1: Standards & Guidance URLs
A2: 1. Identity, Authentication & Session | B2: API Keys & Client Credentials | C2: API-IAM-001 | D2: Dynamic | E2: application authentication, external identity provider, OAuth client and token-enabled API surface | F2: API-key scope enforcement | G2: Verify that aPI-key scope enforcement is securely implemented for the scoped surface and cannot be bypassed by an unauthorised, lower-privilege or malformed request context. | H2: Applicable when the API exposes the referenced capability or trust boundary. | I2: Applicable if this authentication mechanism exists | J2: Execute when the scoped surface uses the referenced identity, token, session, credential or recovery capability. | K2: The capability for 'API-key scope enforcement' is confirmed in scope; the exact route, component or configuration object and version are mapped; a successful authorised baseline has been captured; required valid and negative credential/session states are prepared and identity telemetry is accessible; evidence capture and redaction method are ready; authorisation and operational contacts are confirmed. | L2: Non-blocking companions | M2: None identified | N2: API-BFLA-001 | O2: Use configuration baseline as corroborating evidence where available. | P2: Not Required | Q2: Wave 1 - Foundation | R2: EVD-IAM-API-KEYS-CLIENT-BASE | S2: TDATA-IAM-API-KEYS-CLIENT-BASE | T2: None identified | U2: PAR-W1-IAM | V2: Not waived | W2: Not applicable unless Dependency Gate is Waived. If waived, record approver, equivalent evidence, residual uncertainty and expiry/review date. | X2: Valid authenticated user; clean unauthenticated client; controlled invalid, expired, revoked or out-of-context credential variants as applicable. | Y2: Approved test account and controlled credential/token/session variants representing valid, invalid, expired, revoked, replayed and wrong-context states as applicable. | Z2: Authorised test environment representative of production security controls; production testing only where explicitly approved and operationally coordinated. | AA2: Shared responsibility | AB2: platform controls plus The organisation configuration/custom logic | AC2: For 'API-key scope enforcement': The API/data owner defines the minimum authorised response; application authorisation, object/field policy, gateway controls and backing-service permissions enforce exposure. Confirm named accountable teams during scoping. | AD2: For 'API-key scope enforcement': The API product owner approves behaviour; application engineering changes logic; platform/IAM/gateway or data-service owners change policy and enforcement. Confirm named accountable teams during scoping. | AE2: For 'API-key scope enforcement', execute or review as the representative low-privilege authenticated user, a different-role comparison user and an unauthenticated control client where the route is externally reachable. | AF2: Roles for 'API-key scope enforcement': lowest intended consumer role; second role with different entitlement; unauthenticated control where exposed. Replace role classes with actual named roles during assessment setup. | AG2: Target mapping for 'API-key scope enforcement': record the exact login/token/session/recovery/key endpoint, identity-provider/client policy and protected comparison API operation, including environment, version/build, host/base path and owner. Do not mark Ready until mapped. | AH2: Method for 'API-key scope enforcement': capture an authorised baseline; modify only the control-relevant identity, identifier, field, header, parameter, state or trust input; compare status, body, timing, state and logs. Record variants and stop conditions before execution. | AI2: A low-privilege or out-of-context identity attempts to abuse 'api-key scope enforcement' by bypassing the intended control through alternate routes, contexts or malformed inputs to obtain unauthorised data, action, trust or service impact. | AJ2: Not directly applicable to this control. During route discovery, still confirm that any record-bearing request enforces object and tenant boundaries; otherwise cross-reference a dedicated BOLA test. | AK2: Repeat 'api-key scope enforcement' with the lowest authorised role and compare with the approved elevated role; verify server-side function, object, field and workflow-state authorisation. | AL2: For 'api-key scope enforcement', vary identifiers, duplicates, null/blank values, type and length boundaries, unsupported fields, encodings and safe malformed variants relevant to the parser; verify deterministic allowlisting and binding. | AM2: For 'api-key scope enforcement', compare returned or observable data with business need and role visibility; inspect fields, nested objects, metadata, error detail, timing, result limits, logs and cached artefacts for unnecessary disclosure. | AN2: Repeat 'api-key scope enforcement' without a session and using the public or guest context; verify no protected data, action, file, metadata or record-existence signal is available. | AO2: Identify the relevant endpoint and baseline authorized behavior. Execute a controlled negative test for: api-key scope enforcement. Compare authorization, state, response, timing, and audit evidence. | AP2: Use only authorised scope and synthetic or approved test data; stop immediately if protected real data is exposed or unexpected state change occurs; redact secrets and personal data from evidence. | AQ2: Restore the test object, account or session to its recorded baseline; delete synthetic records, tokens, links or files created solely for testing; confirm no queued job, callback or downstream operation remains pending. | AR2: For 'API-key scope enforcement', protected behaviour is: the control operates consistently across intended and negative contexts, fails securely and leaves objective evidence. No unauthorised data, state change, trust expansion or sensitive diagnostic detail is produced. | AS2: PASS when the observed result matches the defined protected behaviour with no data, state, trust or availability weakness. FAIL when the result deviates from the protected behaviour or leaves the control unverifiable. Record the decision against 'api-key scope enforcement'. | AT2: The control for api-key scope enforcement is absent, inconsistently applied or bypassable, indicating a likely authentication and password management weakness across the affected target API and connected-service trust boundary. | AU2: A valid denial or compliant review for 'API-key scope enforcement' suggests identity, credential, token or session validation is effective for the tested context. It does not prove alternate roles, routes, versions, batch paths or trust boundaries; validate the next representative variant. | AV2: Repeat 'API-key scope enforcement' across a second role, alternate API/UI route, related object, batch/composite path and integration context; review telemetry and configuration for systemic coverage. | AW2: If 'API-key scope enforcement' fails, likely impact includes account or service identity compromise and persistent unauthorised access. Primary affected parties: users, service principals and connected services. Current inherent severity is Critical; confirm exposure, data sensitivity, reachability and blast radius before final rating. | AX2: API2:2023 - Broken Authentication | AY2: A07:2025 - Authentication Failures | AZ2: IA | BA2: Critical | BB2: 25 | BC2: P0 - Immediate | BD2: Candidate | BE2: Pending execution | BF2: Unassigned | BG2: Pending execution. Record the observed behaviour, affected data or state, and evidence-based pass/fail rationale. | BH2: Evidence for 'API-key scope enforcement' must include: test ID, date, tester and environment; exact target/component and version; tested identity, role, entitlement and comparison context; expected result, actual result and decision rationale; redacted evidence links and relevant correlation or trace ID; authorised baseline request/response; control-relevant negative request/response; status, headers, body, timing and before/after state. | BI2: Pending execution: link or ID for requests, responses, screenshots, logs, artefacts and correlation records. | BJ2: Pending execution: identify the actual enforcing control or state that no effective control was observed. | BK2: Unassigned: assign only after scope confirmation or finding triage. | BL2: Not raised | BM2: Not Retested | BN2: Execution note for 'API-key scope enforcement': replace all planning placeholders with observed evidence. This test is evidence-backed only for the executed route, role, method, data context and environment. Record untested variants, exclusions and residual risk. | BO2: https://owasp.org/API-Security/editions/2023/en/0x11-t10/ https://owasp.org/Top10/2025/ https://owasp.org/www-project-secure-coding-practices-quick-reference-guide/stable-en/02-checklist/05-checklist.html
A3: 1. Identity, Authentication & Session | B3: Token Validation & JWT | C3: API-IAM-002 | D3: Dynamic | E3: application authentication, external identity provider, OAuth client and token-enabled API surface | F3: Invalid signature rejection | G3: Verify that invalid signature rejection is securely implemented for the scoped surface and cannot be bypassed by an unauthorised, lower-privilege or malformed request context. | H3: Applicable when the API exposes the referenced capability or trust boundary. | I3: Applicable if this authentication mechanism exists | J3: Execute when the scoped surface uses the referenced identity, token, session, credential or recovery capability. | K3: The capability for 'Invalid signature rejection' is confirmed in scope; the exact route, component or configuration object and version are mapped; a successful authorised baseline has been captured; required valid and negative credential/session states are prepared and identity telemetry is accessible; evidence capture and redaction method are ready; authorisation and operational contacts are confirmed. | L3: Non-blocking companions | M3: None identified | N3: API-BFLA-001 | O3: Use configuration baseline as corroborating evidence where available. | P3: Not Required | Q3: Wave 1 - Foundation | R3: EVD-IAM-TOKEN-VALIDATION-BASE | S3: TDATA-IAM-TOKEN-VALIDATION-BASE | T3: None identified | U3: PAR-W1-IAM | V3: Not waived | W3: Not applicable unless Dependency Gate is Waived. If waived, record approver, equivalent evidence, residual uncertainty and expiry/review date. | X3: Valid authenticated user; clean unauthenticated client; controlled invalid, expired, revoked or out-of-context credential variants as applicable. | Y3: Approved test account and controlled credential/token/session variants representing valid, invalid, expired, revoked, replayed and wrong-context states as applicable. | Z3: Authorised test environment representative of production security controls; production testing only where explicitly approved and operationally coordinated. | AA3: Shared responsibility | AB3: platform controls plus The organisation configuration/custom logic | AC3: For 'Invalid signature rejection': The API/data owner defines the minimum authorised response; application authorisation, object/field policy, gateway controls and backing-service permissions enforce exposure. Confirm named accountable teams during scoping. | AD3: For 'Invalid signature rejection': The API product owner approves behaviour; application engineering changes logic; platform/IAM/gateway or data-service owners change policy and enforcement. Confirm named accountable teams during scoping. | AE3: For 'Invalid signature rejection', execute or review as the representative low-privilege authenticated user, a different-role comparison user and an unauthenticated control client where the route is externally reachable. | AF3: Roles for 'Invalid signature rejection': lowest intended consumer role; second role with different entitlement; unauthenticated control where exposed. Replace role classes with actual named roles during assessment setup. | AG3: Target mapping for 'Invalid signature rejection': record the exact login/token/session/recovery/key endpoint, identity-provider/client policy and protected comparison API operation, including environment, version/build, host/base path and owner. Do not mark Ready until mapped. | AH3: Method for 'Invalid signature rejection': capture an authorised baseline; modify only the control-relevant identity, identifier, field, header, parameter, state or trust input; compare status, body, timing, state and logs. Record variants and stop conditions before execution. | AI3: A low-privilege or out-of-context identity attempts to abuse 'invalid signature rejection' by bypassing the intended control through alternate routes, contexts or malformed inputs to obtain unauthorised data, action, trust or service impact. | AJ3: Not directly applicable to this control. During route discovery, still confirm that any record-bearing request enforces object and tenant boundaries; otherwise cross-reference a dedicated BOLA test. | AK3: Repeat 'invalid signature rejection' with the lowest authorised role and compare with the approved elevated role; verify server-side function, object, field and workflow-state authorisation. | AL3: For 'invalid signature rejection', vary identifiers, duplicates, null/blank values, type and length boundaries, unsupported fields, encodings and safe malformed variants relevant to the parser; verify deterministic allowlisting and binding. | AM3: For 'invalid signature rejection', compare returned or observable data with business need and role visibility; inspect fields, nested objects, metadata, error detail, timing, result limits, logs and cached artefacts for unnecessary disclosure. | AN3: Repeat 'invalid signature rejection' without a session and using the public or guest context; verify no protected data, action, file, metadata or record-existence signal is available. | AO3: Identify the relevant endpoint and baseline authorized behavior. Execute a controlled negative test for: invalid signature rejection. Compare authorization, state, response, timing, and audit evidence. | AP3: Use only authorised scope and synthetic or approved test data; stop immediately if protected real data is exposed or unexpected state change occurs; redact secrets and personal data from evidence. | AQ3: Restore the test object, account or session to its recorded baseline; delete synthetic records, tokens, links or files created solely for testing; confirm no queued job, callback or downstream operation remains pending. | AR3: For 'Invalid signature rejection', protected behaviour is: the control operates consistently across intended and negative contexts, fails securely and leaves objective evidence. No unauthorised data, state change, trust expansion or sensitive diagnostic detail is produced. | AS3: PASS when the observed result matches the defined protected behaviour with no data, state, trust or availability weakness. FAIL when the result deviates from the protected behaviour or leaves the control unverifiable. Record the decision against 'invalid signature rejection'. | AT3: The control for invalid signature rejection is absent, inconsistently applied or bypassable, indicating a likely authentication and password management weakness across the affected target API and connected-service trust boundary. | AU3: A valid denial or compliant review for 'Invalid signature rejection' suggests identity, credential, token or session validation is effective for the tested context. It does not prove alternate roles, routes, versions, batch paths or trust boundaries; validate the next representative variant. | AV3: Repeat 'Invalid signature rejection' across a second role, alternate API/UI route, related object, batch/composite path and integration context; review telemetry and configuration for systemic coverage. | AW3: If 'Invalid signature rejection' fails, likely impact includes account or service identity compromise and persistent unauthorised access. Primary affected parties: users, service principals and connected services. Current inherent severity is Critical; confirm exposure, data sensitivity, reachability and blast radius before final rating. | AX3: API2:2023 - Broken Authentication | AY3: A07:2025 - Authentication Failures | AZ3: IA | BA3: Critical | BB3: 25 | BC3: P0 - Immediate | BD3: Candidate | BE3: Pending execution | BF3: Unassigned | BG3: Pending execution. Record the observed behaviour, affected data or state, and evidence-based pass/fail rationale. | BH3: Evidence for 'Invalid signature rejection' must include: test ID, date, tester and environment; exact target/component and version; tested identity, role, entitlement and comparison context; expected result, actual result and decision rationale; redacted evidence links and relevant correlation or trace ID; authorised baseline request/response; control-relevant negative request/response; status, headers, body, timing and before/after state. | BI3: Pending execution: link or ID for requests, responses, screenshots, logs, artefacts and correlation records. | BJ3: Pending execution: identify the actual enforcing control or state that no effective control was observed. | BK3: Unassigned: assign only after scope confirmation or finding triage. | BL3: Not raised | BM3: Not Retested | BN3: Execution note for 'Invalid signature rejection': replace all planning placeholders with observed evidence. This test is evidence-backed only for the executed route, role, method, data context and environment. Record untested variants, exclusions and residual risk. | BO3: https://owasp.org/API-Security/editions/2023/en/0x11-t10/ https://owasp.org/Top10/2025/ https://owasp.org/www-project-secure-coding-practices-quick-reference-guide/stable-en/02-checklist/05-checklist.html
A4: 1. Identity, Authentication & Session | B4: API Keys & Client Credentials | C4: API-IAM-003 | D4: Dynamic | E4: application authentication, external identity provider, OAuth client and token-enabled API surface | F4: API-key expiry and revocation | G4: Verify that aPI-key expiry and revocation is securely implemented for the scoped surface and cannot be bypassed by an unauthorised, lower-privilege or malformed request context. | H4: Applicable when the API exposes the referenced capability or trust boundary. | I4: Applicable if this authentication mechanism exists | J4: Execute when the scoped surface uses the referenced identity, token, session, credential or recovery capability. | K4: The capability for 'API-key expiry and revocation' is confirmed in scope; the exact route, component or configuration object and version are mapped; a successful authorised baseline has been captured; required valid and negative credential/session states are prepared and identity telemetry is accessible; evidence capture and redaction method are ready; authorisation and operational contacts are confirmed. | L4: Blocking prerequisites + non-blocking companions | M4: API-IAM-001 | N4: API-BFLA-001 | O4: Establish the baseline control behaviour for 'API Keys & Client Credentials' before testing this variant. Use configuration baseline as corroborating evidence where available. | P4: Not Assessed | Q4: Wave 2 - Control Variants | R4: EVD-IAM-API-KEYS-CLIENT-BASE | S4: TDATA-IAM-API-KEYS-CLIENT-BASE | T4: API-IAM-001 | U4: PAR-W2-IAM | V4: Not waived | W4: Not applicable unless Dependency Gate is Waived. If waived, record approver, equivalent evidence, residual uncertainty and expiry/review date. | X4: Valid authenticated user; clean unauthenticated client; controlled invalid, expired, revoked or out-of-context credential variants as applicable. | Y4: Approved test account and controlled credential/token/session variants representing valid, invalid, expired, revoked, replayed and wrong-context states as applicable. | Z4: Authorised test environment representative of production security controls; production testing only where explicitly approved and operationally coordinated. | AA4: Shared responsibility | AB4: platform controls plus The organisation configuration/custom logic | AC4: For 'API-key expiry and revocation': The API/data owner defines the minimum authorised response; application authorisation, object/field policy, gateway controls and backing-service permissions enforce exposure. Confirm named accountable teams during scoping. | AD4: For 'API-key expiry and revocation': The API product owner approves behaviour; application engineering changes logic; platform/IAM/gateway or data-service owners change policy and enforcement. Confirm named accountable teams during scoping. | AE4: For 'API-key expiry and revocation', execute or review as the representative low-privilege authenticated user, a different-role comparison user and an unauthenticated control client where the route is externally reachable. | AF4: Roles for 'API-key expiry and revocation': lowest intended consumer role; second role with different entitlement; unauthenticated control where exposed. Replace role classes with actual named roles during assessment setup. | AG4: Target mapping for 'API-key expiry and revocation': record the exact login/token/session/recovery/key endpoint, identity-provider/client policy and protected comparison API operation, including environment, version/build, host/base path and owner. Do not mark Ready until mapped. | AH4: Method for 'API-key expiry and revocation': capture an authorised baseline; modify only the control-relevant identity, identifier, field, header, parameter, state or trust input; compare status, body, timing, state and logs. Record variants and stop conditions before execution. | AI4: A low-privilege or out-of-context identity attempts to abuse 'api-key expiry and revocation' by bypassing the intended control through alternate routes, contexts or malformed inputs to obtain unauthorised data, action, trust or service impact. | AJ4: Not directly applicable to this control. During route discovery, still confirm that any record-bearing request enforces object and tenant boundaries; otherwise cross-reference a dedicated BOLA test. | AK4: Repeat 'api-key expiry and revocation' with the lowest authorised role and compare with the approved elevated role; verify server-side function, object, field and workflow-state authorisation. | AL4: For 'api-key expiry and revocation', vary identifiers, duplicates, null/blank values, type and length boundaries, unsupported fields, encodings and safe malformed variants relevant to the parser; verify deterministic allowlisting and binding. | AM4: For 'api-key expiry and revocation', compare returned or observable data with business need and role visibility; inspect fields, nested objects, metadata, error detail, timing, result limits, logs and cached artefacts for unnecessary disclosure. | AN4: Repeat 'api-key expiry and revocation' without a session and using the public or guest context; verify no protected data, action, file, metadata or record-existence signal is available. | AO4: Identify the relevant endpoint and baseline authorized behavior. Execute a controlled negative test for: api-key expiry and revocation. Compare authorization, state, response, timing, and audit evidence. | AP4: Use only authorised scope and synthetic or approved test data; stop immediately if protected real data is exposed or unexpected state change occurs; redact secrets and personal data from evidence. | AQ4: Restore the test object, account or session to its recorded baseline; delete synthetic records, tokens, links or files created solely for testing; confirm no queued job, callback or downstream operation remains pending. | AR4: For 'API-key expiry and revocation', protected behaviour is: the control operates consistently across intended and negative contexts, fails securely and leaves objective evidence. No unauthorised data, state change, trust expansion or sensitive diagnostic detail is produced. | AS4: PASS when the observed result matches the defined protected behaviour with no data, state, trust or availability weakness. FAIL when the result deviates from the protected behaviour or leaves the control unverifiable. Record the decision against 'api-key expiry and revocation'. | AT4: The control for api-key expiry and revocation is absent, inconsistently applied or bypassable, indicating a likely authentication and password management weakness across the affected target API and connected-service trust boundary. | AU4: A valid denial or compliant review for 'API-key expiry and revocation' suggests identity, credential, token or session validation is effective for the tested context. It does not prove alternate roles, routes, versions, batch paths or trust boundaries; validate the next representative variant. | AV4: Repeat 'API-key expiry and revocation' across a second role, alternate API/UI route, related object, batch/composite path and integration context; review telemetry and configuration for systemic coverage. | AW4: If 'API-key expiry and revocation' fails, likely impact includes account or service identity compromise and persistent unauthorised access. Primary affected parties: users, service principals and connected services. Current inherent severity is High; confirm exposure, data sensitivity, reachability and blast radius before final rating. | AX4: API2:2023 - Broken Authentication | AY4: A07:2025 - Authentication Failures | AZ4: IA | BA4: High | BB4: 16 | BC4: P1 - High | BD4: Candidate | BE4: Pending execution | BF4: Unassigned | BG4: Pending execution. Record the observed behaviour, affected data or state, and evidence-based pass/fail rationale. | BH4: Evidence for 'API-key expiry and revocation' must include: test ID, date, tester and environment; exact target/component and version; tested identity, role, entitlement and comparison context; expected result, actual result and decision rationale; redacted evidence links and relevant correlation or trace ID; authorised baseline request/response; control-relevant negative request/response; status, headers, body, timing and before/after state. | BI4: Pending execution: link or ID for requests, responses, screenshots, logs, artefacts and correlation records. | BJ4: Pending execution: identify the actual enforcing control or state that no effective control was observed. | BK4: Unassigned: assign only after scope confirmation or finding triage. | BL4: Not raised | BM4: Not Retested | BN4: Execution note for 'API-key expiry and revocation': replace all planning placeholders with observed evidence. This test is evidence-backed only for the executed route, role, method, data context and environment. Record untested variants, exclusions and residual risk. | BO4: https://owasp.org/API-Security/editions/2023/en/0x11-t10/ https://owasp.org/Top10/2025/ https://owasp.org/www-project-secure-coding-practices-quick-reference-guide/stable-en/02-checklist/05-checklist.html
A5: 1. Identity, Authentication & Session | B5: Token Validation & JWT | C5: API-IAM-004 | D5: Dynamic | E5: application authentication, external identity provider, OAuth client and token-enabled API surface | F5: Account enumeration resistance | G5: Verify that account enumeration resistance is securely implemented for the scoped surface and cannot be bypassed by an unauthorised, lower-privilege or malformed request context. | H5: Applicable when the API exposes the referenced capability or trust boundary. | I5: Applicable if this authentication mechanism exists | J5: Execute when the scoped surface uses the referenced identity, token, session, credential or recovery capability. | K5: The capability for 'Account enumeration resistance' is confirmed in scope; the exact route, component or configuration object and version are mapped; a successful authorised baseline has been captured; required valid and negative credential/session states are prepared and identity telemetry is accessible; safe request thresholds, monitoring owner and stop conditions are approved; evidence capture and redaction method are ready; authorisation and operational contacts are confirmed. | L5: Blocking prerequisites + non-blocking companions | M5: API-IAM-002, API-BFLA-015 | N5: API-IAM-016, API-BFLA-001 | O5: Establish the baseline control behaviour for 'Token Validation & JWT' before testing this variant. Confirm telemetry and correlation are available before abuse-pattern testing. Use the approved baseline threshold and stop-condition model. Use configuration baseline as corroborating evidence where available. | P5: Not Assessed | Q5: Wave 2 - Control Variants | R5: EVD-IAM-TOKEN-VALIDATION-BASE | S5: TDATA-IAM-TOKEN-VALIDATION-BASE | T5: API-IAM-002, API-BFLA-015 | U5: PAR-W2-IAM | V5: Not waived | W5: Not applicable unless Dependency Gate is Waived. If waived, record approver, equivalent evidence, residual uncertainty and expiry/review date. | X5: Valid authenticated user; clean unauthenticated client; controlled invalid, expired, revoked or out-of-context credential variants as applicable. | Y5: Approved test account and controlled credential/token/session variants representing valid, invalid, expired, revoked, replayed and wrong-context states as applicable. | Z5: Non-production or safely isolated environment preferred; if production is authorised, use agreed thresholds, synthetic data, monitoring and immediate stop authority. | AA5: Shared responsibility | AB5: platform controls plus The organisation configuration/custom logic | AC5: For 'Account enumeration resistance': The API/data owner defines the minimum authorised response; application authorisation, object/field policy, gateway controls and backing-service permissions enforce exposure. Confirm named accountable teams during scoping. | AD5: For 'Account enumeration resistance': The API product owner approves behaviour; application engineering changes logic; platform/IAM/gateway or data-service owners change policy and enforcement. Confirm named accountable teams during scoping. | AE5: For 'Account enumeration resistance', execute or review as the representative low-privilege authenticated user, a different-role comparison user and an unauthenticated control client where the route is externally reachable. | AF5: Roles for 'Account enumeration resistance': lowest intended consumer role; second role with different entitlement; unauthenticated control where exposed. Replace role classes with actual named roles during assessment setup. | AG5: Target mapping for 'Account enumeration resistance': record the exact login/token/session/recovery/key endpoint, identity-provider/client policy and protected comparison API operation, including environment, version/build, host/base path and owner. Do not mark Ready until mapped. | AH5: Method for 'Account enumeration resistance': capture a normal baseline; execute a controlled stepped-volume or patterned sequence below approved thresholds; observe limits, latency, errors, telemetry and recovery. Record variants and stop conditions before execution. | AI5: A low-privilege or out-of-context identity attempts to abuse 'account enumeration resistance' by increasing request rate, volume, cost or enumeration pattern within approved limits to obtain unauthorised data, action, trust or service impact. | AJ5: Not directly applicable to this control. During route discovery, still confirm that any record-bearing request enforces object and tenant boundaries; otherwise cross-reference a dedicated BOLA test. | AK5: Repeat 'account enumeration resistance' with the lowest authorised role and compare with the approved elevated role; verify server-side function, object, field and workflow-state authorisation. | AL5: For 'account enumeration resistance', vary identifiers, duplicates, null/blank values, type and length boundaries, unsupported fields, encodings and safe malformed variants relevant to the parser; verify deterministic allowlisting and binding. | AM5: For 'account enumeration resistance', compare returned or observable data with business need and role visibility; inspect fields, nested objects, metadata, error detail, timing, result limits, logs and cached artefacts for unnecessary disclosure. | AN5: Repeat 'account enumeration resistance' without a session and using the public or guest context; verify no protected data, action, file, metadata or record-existence signal is available. | AO5: Identify the relevant endpoint and baseline authorized behavior. Execute a controlled negative test for: account enumeration resistance. Compare authorization, state, response, timing, and audit evidence. | AP5: Use only authorised scope and synthetic or approved test data; stop immediately if protected real data is exposed or unexpected state change occurs; redact secrets and personal data from evidence; stay below the approved request threshold and stop on latency, error-rate or availability degradation. | AQ5: Restore the test object, account or session to its recorded baseline; delete synthetic records, tokens, links or files created solely for testing; confirm no queued job, callback or downstream operation remains pending; allow rate or resource counters to recover and confirm service health with the monitoring owner. | AR5: For 'Account enumeration resistance', protected behaviour is: limits and monitoring activate before harmful extraction, cost or degradation and service recovers predictably. No unauthorised data, state change, trust expansion or sensitive diagnostic detail is produced. | AS5: PASS when limits, back-pressure and monitoring activate before harmful impact. FAIL when approved-volume testing demonstrates uncontrolled cost, extraction, enumeration or degradation. Record the decision against 'account enumeration resistance'. | AT5: The control for account enumeration resistance is absent, inconsistently applied or bypassable, indicating a likely authentication and password management weakness across the affected target API and connected-service trust boundary. | AU5: A valid denial or compliant review for 'Account enumeration resistance' suggests identity, credential, token or session validation is effective for the tested context. It does not prove alternate roles, routes, versions, batch paths or trust boundaries; validate the next representative variant. | AV5: Repeat 'Account enumeration resistance' across a second role, alternate API/UI route, related object, batch/composite path and integration context; review telemetry and configuration for systemic coverage. | AW5: If 'Account enumeration resistance' fails, likely impact includes account or service identity compromise and persistent unauthorised access, mass extraction, automated abuse, unexpected cost or availability degradation. Primary affected parties: users, service principals and connected services, customers, operations and service owners. Current inherent severity is High; confirm exposure, data sensitivity, reachability and blast radius before final rating. | AX5: API2:2023 - Broken Authentication | AY5: A07:2025 - Authentication Failures | AZ5: IA | BA5: High | BB5: 16 | BC5: P1 - High | BD5: Candidate | BE5: Pending execution | BF5: Unassigned | BG5: Pending execution. Record the observed behaviour, affected data or state, and evidence-based pass/fail rationale. | BH5: Evidence for 'Account enumeration resistance' must include: test ID, date, tester and environment; exact target/component and version; tested identity, role, entitlement and comparison context; expected result, actual result and decision rationale; redacted evidence links and relevant correlation or trace ID; authorised baseline request/response; control-relevant negative request/response; status, headers, body, timing and before/after state. | BI5: Pending execution: link or ID for requests, responses, screenshots, logs, artefacts and correlation records. | BJ5: Pending execution: identify the actual enforcing control or state that no effective control was observed. | BK5: Unassigned: assign only after scope confirmation or finding triage. | BL5: Not raised | BM5: Not Retested | BN5: Execution note for 'Account enumeration resistance': replace all planning placeholders with observed evidence. This test is evidence-backed only for the executed route, role, method, data context and environment. Record untested variants, exclusions and residual risk. | BO5: https://owasp.org/API-Security/editions/2023/en/0x11-t10/ https://owasp.org/Top10/2025/ https://owasp.org/www-project-secure-coding-practices-quick-reference-guide/stable-en/02-checklist/05-checklist.html
A6: 1. Identity, Authentication & Session | B6: Token Validation & JWT | C6: API-IAM-005 | D6: Dynamic | E6: application authentication, external identity provider, OAuth client and token-enabled API surface | F6: Algorithm confusion resistance | G6: Verify that algorithm confusion resistance is securely implemented for the scoped surface and cannot be bypassed by an unauthorised, lower-privilege or malformed request context. | H6: Applicable when the API exposes the referenced capability or trust boundary. | I6: Applicable if this authentication mechanism exists | J6: Execute when the scoped surface uses the referenced identity, token, session, credential or recovery capability. | K6: The capability for 'Algorithm confusion resistance' is confirmed in scope; the exact route, component or configuration object and version are mapped; a successful authorised baseline has been captured; required valid and negative credential/session states are prepared and identity telemetry is accessible; evidence capture and redaction method are ready; authorisation and operational contacts are confirmed. | L6: Blocking prerequisites + non-blocking companions | M6: API-IAM-002 | N6: API-BFLA-001 | O6: Establish the baseline control behaviour for 'Token Validation & JWT' before testing this variant. Use configuration baseline as corroborating evidence where available. | P6: Not Assessed | Q6: Wave 2 - Control Variants | R6: EVD-IAM-TOKEN-VALIDATION-BASE | S6: TDATA-IAM-TOKEN-VALIDATION-BASE | T6: API-IAM-002 | U6: PAR-W2-IAM | V6: Not waived | W6: Not applicable unless Dependency Gate is Waived. If waived, record approver, equivalent evidence, residual uncertainty and expiry/review date. | X6: Valid authenticated user; clean unauthenticated client; controlled invalid, expired, revoked or out-of-context credential variants as applicable. | Y6: Approved test account and controlled credential/token/session variants representing valid, invalid, expired, revoked, replayed and wrong-context states as applicable. | Z6: Authorised test environment representative of production security controls; production testing only where explicitly approved and operationally coordinated. | AA6: Shared responsibility | AB6: platform controls plus The organisation configuration/custom logic | AC6: For 'Algorithm confusion resistance': The API/data owner defines the minimum authorised response; application authorisation, object/field policy, gateway controls and backing-service permissions enforce exposure. Confirm named accountable teams during scoping. | AD6: For 'Algorithm confusion resistance': The API product owner approves behaviour; application engineering changes logic; platform/IAM/gateway or data-service owners change policy and enforcement. Confirm named accountable teams during scoping. | AE6: For 'Algorithm confusion resistance', execute or review as the representative low-privilege authenticated user, a different-role comparison user and an unauthenticated control client where the route is externally reachable. | AF6: Roles for 'Algorithm confusion resistance': lowest intended consumer role; second role with different entitlement; unauthenticated control where exposed. Replace role classes with actual named roles during assessment setup. | AG6: Target mapping for 'Algorithm confusion resistance': record the exact login/token/session/recovery/key endpoint, identity-provider/client policy and protected comparison API operation, including environment, version/build, host/base path and owner. Do not mark Ready until mapped. | AH6: Method for 'Algorithm confusion resistance': capture an authorised baseline; modify only the control-relevant identity, identifier, field, header, parameter, state or trust input; compare status, body, timing, state and logs. Record variants and stop conditions before execution. | AI6: A low-privilege or out-of-context identity attempts to abuse 'algorithm confusion resistance' by bypassing the intended control through alternate routes, contexts or malformed inputs to obtain unauthorised data, action, trust or service impact. | AJ6: Not directly applicable to this control. During route discovery, still confirm that any record-bearing request enforces object and tenant boundaries; otherwise cross-reference a dedicated BOLA test. | AK6: Repeat 'algorithm confusion resistance' with the lowest authorised role and compare with the approved elevated role; verify server-side function, object, field and workflow-state authorisation. | AL6: For 'algorithm confusion resistance', vary identifiers, duplicates, null/blank values, type and length boundaries, unsupported fields, encodings and safe malformed variants relevant to the parser; verify deterministic allowlisting and binding. | AM6: For 'algorithm confusion resistance', compare returned or observable data with business need and role visibility; inspect fields, nested objects, metadata, error detail, timing, result limits, logs and cached artefacts for unnecessary disclosure. | AN6: Repeat 'algorithm confusion resistance' without a session and using the public or guest context; verify no protected data, action, file, metadata or record-existence signal is available. | AO6: Identify the relevant endpoint and baseline authorized behavior. Execute a controlled negative test for: algorithm confusion resistance. Compare authorization, state, response, timing, and audit evidence. | AP6: Use only authorised scope and synthetic or approved test data; stop immediately if protected real data is exposed or unexpected state change occurs; redact secrets and personal data from evidence. | AQ6: Restore the test object, account or session to its recorded baseline; delete synthetic records, tokens, links or files created solely for testing; confirm no queued job, callback or downstream operation remains pending. | AR6: For 'Algorithm confusion resistance', protected behaviour is: the control operates consistently across intended and negative contexts, fails securely and leaves objective evidence. No unauthorised data, state change, trust expansion or sensitive diagnostic detail is produced. | AS6: PASS when the observed result matches the defined protected behaviour with no data, state, trust or availability weakness. FAIL when the result deviates from the protected behaviour or leaves the control unverifiable. Record the decision against 'algorithm confusion resistance'. | AT6: The control for algorithm confusion resistance is absent, inconsistently applied or bypassable, indicating a likely authentication and password management weakness across the affected target API and connected-service trust boundary. | AU6: A valid denial or compliant review for 'Algorithm confusion resistance' suggests identity, credential, token or session validation is effective for the tested context. It does not prove alternate roles, routes, versions, batch paths or trust boundaries; validate the next representative variant. | AV6: Repeat 'Algorithm confusion resistance' across a second role, alternate API/UI route, related object, batch/composite path and integration context; review telemetry and configuration for systemic coverage. | AW6: If 'Algorithm confusion resistance' fails, likely impact includes account or service identity compromise and persistent unauthorised access. Primary affected parties: users, service principals and connected services. Current inherent severity is High; confirm exposure, data sensitivity, reachability and blast radius before final rating. | AX6: API2:2023 - Broken Authentication | AY6: A07:2025 - Authentication Failures | AZ6: IA | BA6: High | BB6: 16 | BC6: P1 - High | BD6: Candidate | BE6: Pending execution | BF6: Unassigned | BG6: Pending execution. Record the observed behaviour, affected data or state, and evidence-based pass/fail rationale. | BH6: Evidence for 'Algorithm confusion resistance' must include: test ID, date, tester and environment; exact target/component and version; tested identity, role, entitlement and comparison context; expected result, actual result and decision rationale; redacted evidence links and relevant correlation or trace ID; authorised baseline request/response; control-relevant negative request/response; status, headers, body, timing and before/after state. | BI6: Pending execution: link or ID for requests, responses, screenshots, logs, artefacts and correlation records. | BJ6: Pending execution: identify the actual enforcing control or state that no effective control was observed. | BK6: Unassigned: assign only after scope confirmation or finding triage. | BL6: Not raised | BM6: Not Retested | BN6: Execution note for 'Algorithm confusion resistance': replace all planning placeholders with observed evidence. This test is evidence-backed only for the executed route, role, method, data context and environment. Record untested variants, exclusions and residual risk. | BO6: https://owasp.org/API-Security/editions/2023/en/0x11-t10/ https://owasp.org/Top10/2025/ https://owasp.org/www-project-secure-coding-practices-quick-reference-guide/stable-en/02-checklist/05-checklist.html
A7: 1. Identity, Authentication & Session | B7: Token Validation & JWT | C7: API-IAM-006 | D7: Hybrid | E7: application authentication, external identity provider, OAuth client and token-enabled API surface | F7: Apply MFA or step-up authentication where risk requires | G7: Verify that apply MFA or step-up authentication where risk requires is securely implemented for the scoped surface and cannot be bypassed by an unauthorised, lower-privilege or malformed request context. | H7: Applicable by default; mark N/A only with documented architecture or data-flow justification. | I7: Applicable if this authentication mechanism exists | J7: Execute when the scoped surface uses the referenced identity, token, session, credential or recovery capability. | K7: The capability for 'Apply MFA or step-up authentication where risk requires' is confirmed in scope; the exact route, component or configuration object and version are mapped; a successful authorised baseline has been captured; required valid and negative credential/session states are prepared and identity telemetry is accessible; evidence capture and redaction method are ready; authorisation and operational contacts are confirmed. | L7: Blocking prerequisites | M7: API-IAM-002 | N7: None identified | O7: Establish the baseline control behaviour for 'Token Validation & JWT' before testing this variant. | P7: Not Assessed | Q7: Wave 2 - Control Variants | R7: EVD-IAM-TOKEN-VALIDATION-BASE | S7: TDATA-IAM-TOKEN-VALIDATION-BASE | T7: API-IAM-002 | U7: PAR-W2-IAM | V7: Not waived | W7: Not applicable unless Dependency Gate is Waived. If waived, record approver, equivalent evidence, residual uncertainty and expiry/review date. | X7: Valid authenticated user; clean unauthenticated client; controlled invalid, expired, revoked or out-of-context credential variants as applicable. | Y7: Approved test account and controlled credential/token/session variants representing valid, invalid, expired, revoked, replayed and wrong-context states as applicable. | Z7: Authorised test environment representative of production security controls; production testing only where explicitly approved and operationally coordinated. | AA7: Shared responsibility | AB7: platform controls plus The organisation configuration/custom logic | AC7: For 'Apply MFA or step-up authentication where risk requires': The API/data owner defines the minimum authorised response; application authorisation, object/field policy, gateway controls and backing-service permissions enforce exposure. Confirm named accountable teams during scoping. | AD7: For 'Apply MFA or step-up authentication where risk requires': The API product owner approves behaviour; application engineering changes logic; platform/IAM/gateway or data-service owners change policy and enforcement. Confirm named accountable teams during scoping. | AE7: For 'Apply MFA or step-up authentication where risk requires', execute or review as the representative low-privilege authenticated user, a different-role comparison user and an unauthenticated control client where the route is externally reachable. | AF7: Roles for 'Apply MFA or step-up authentication where risk requires': lowest intended consumer role; second role with different entitlement; unauthenticated control where exposed. Replace role classes with actual named roles during assessment setup. | AG7: Target mapping for 'Apply MFA or step-up authentication where risk requires': record the exact login/token/session/recovery/key endpoint, identity-provider/client policy and protected comparison API operation, including environment, version/build, host/base path and owner. Do not mark Ready until mapped. | AH7: Method for 'Apply MFA or step-up authentication where risk requires': capture an authorised baseline; modify only the control-relevant identity, identifier, field, header, parameter, state or trust input; compare status, body, timing, state and logs. Record variants and stop conditions before execution. | AI7: A low-privilege or out-of-context identity attempts to abuse 'apply mfa or step-up authentication where risk requires' by bypassing the intended control through alternate routes, contexts or malformed inputs to obtain unauthorised data, action, trust or service impact. | AJ7: Not directly applicable to this control. During route discovery, still confirm that any record-bearing request enforces object and tenant boundaries; otherwise cross-reference a dedicated BOLA test. | AK7: Repeat 'apply mfa or step-up authentication where risk requires' with the lowest authorised role and compare with the approved elevated role; verify server-side function, object, field and workflow-state authorisation. | AL7: For 'apply mfa or step-up authentication where risk requires', vary identifiers, duplicates, null/blank values, type and length boundaries, unsupported fields, encodings and safe malformed variants relevant to the parser; verify deterministic allowlisting and binding. | AM7: For 'apply mfa or step-up authentication where risk requires', compare returned or observable data with business need and role visibility; inspect fields, nested objects, metadata, error detail, timing, result limits, logs and cached artefacts for unnecessary disclosure. | AN7: Repeat 'apply mfa or step-up authentication where risk requires' without a session and using the public or guest context; verify no protected data, action, file, metadata or record-existence signal is available. | AO7: Review implementation evidence and execute a targeted API validation to verify: apply mfa or step-up authentication where risk requires. Confirm enforcement at the trusted server-side boundary and test negative/error behavior. | AP7: Use only authorised scope and synthetic or approved test data; stop immediately if protected real data is exposed or unexpected state change occurs; redact secrets and personal data from evidence. | AQ7: Restore the test object, account or session to its recorded baseline; delete synthetic records, tokens, links or files created solely for testing; confirm no queued job, callback or downstream operation remains pending. | AR7: For 'Apply MFA or step-up authentication where risk requires', protected behaviour is: the control operates consistently across intended and negative contexts, fails securely and leaves objective evidence. No unauthorised data, state change, trust expansion or sensitive diagnostic detail is produced. | AS7: PASS when the observed result matches the defined protected behaviour with no data, state, trust or availability weakness. FAIL when the result deviates from the protected behaviour or leaves the control unverifiable. Record the decision against 'apply mfa or step-up authentication where risk requires'. | AT7: The control for apply mfa or step-up authentication where risk requires is absent, inconsistently applied or bypassable, indicating a likely authentication and password management weakness across the affected target API and connected-service trust boundary. | AU7: A valid denial or compliant review for 'Apply MFA or step-up authentication where risk requires' suggests identity, credential, token or session validation is effective for the tested context. It does not prove alternate roles, routes, versions, batch paths or trust boundaries; validate the next representative variant. | AV7: Repeat 'Apply MFA or step-up authentication where risk requires' across a second role, alternate API/UI route, related object, batch/composite path and integration context; review telemetry and configuration for systemic coverage. | AW7: If 'Apply MFA or step-up authentication where risk requires' fails, likely impact includes account or service identity compromise and persistent unauthorised access. Primary affected parties: users, service principals and connected services. Current inherent severity is High; confirm exposure, data sensitivity, reachability and blast radius before final rating. | AX7: API2:2023 - Broken Authentication | AY7: A07:2025 - Authentication Failures | AZ7: IA | BA7: High | BB7: 16 | BC7: P1 - High | BD7: Candidate | BE7: Pending execution | BF7: Unassigned | BG7: Pending execution. Record the observed behaviour, affected data or state, and evidence-based pass/fail rationale. | BH7: Evidence for 'Apply MFA or step-up authentication where risk requires' must include: test ID, date, tester and environment; exact target/component and version; tested identity, role, entitlement and comparison context; expected result, actual result and decision rationale; redacted evidence links and relevant correlation or trace ID; authorised baseline request/response; control-relevant negative request/response; status, headers, body, timing and before/after state. | BI7: Pending execution: link or ID for requests, responses, screenshots, logs, artefacts and correlation records. | BJ7: Pending execution: identify the actual enforcing control or state that no effective control was observed. | BK7: Unassigned: assign only after scope confirmation or finding triage. | BL7: Not raised | BM7: Not Retested | BN7: Execution note for 'Apply MFA or step-up authentication where risk requires': replace all planning placeholders with observed evidence. This test is evidence-backed only for the executed route, role, method, data context and environment. Record untested variants, exclusions and residual risk. | BO7: https://owasp.org/API-Security/editions/2023/en/0x11-t10/ https://owasp.org/Top10/2025/ https://owasp.org/www-project-secure-coding-practices-quick-reference-guide/stable-en/02-checklist/05-checklist.html
A8: 1. Identity, Authentication & Session | B8: Session Lifecycle & Cookies | C8: API-IAM-007 | D8: Hybrid | E8: browser session, portal cookie and API session handling | F8: Apply absolute session timeout | G8: Verify that apply absolute session timeout is securely implemented for the scoped surface and cannot be bypassed by an unauthorised, lower-privilege or malformed request context. | H8: Applicable by default; mark N/A only with documented architecture or data-flow justification. | I8: Applicable if this authentication mechanism exists | J8: Execute when the scoped surface uses the referenced identity, token, session, credential or recovery capability. | K8: The capability for 'Apply absolute session timeout' is confirmed in scope; the exact route, component or configuration object and version are mapped; a successful authorised baseline has been captured; required valid and negative credential/session states are prepared and identity telemetry is accessible; evidence capture and redaction method are ready; authorisation and operational contacts are confirmed. | L8: Standalone / no catalogue dependency identified | M8: None identified | N8: None identified | O8: The test can be executed independently once its own preconditions are met. | P8: Not Required | Q8: Wave 1 - Foundation | R8: EVD-IAM-SESSION-LIFECYCL-BASE | S8: TDATA-IAM-SESSION-LIFECYCL-BASE | T8: None identified | U8: PAR-W1-IAM | V8: Not waived | W8: Not applicable unless Dependency Gate is Waived. If waived, record approver, equivalent evidence, residual uncertainty and expiry/review date. | X8: Valid authenticated user; clean unauthenticated client; controlled invalid, expired, revoked or out-of-context credential variants as applicable. | Y8: Approved test account and controlled credential/token/session variants representing valid, invalid, expired, revoked, replayed and wrong-context states as applicable. | Z8: Authorised test environment representative of production security controls; production testing only where explicitly approved and operationally coordinated. | AA8: Shared responsibility | AB8: platform controls plus The organisation configuration/custom logic | AC8: For 'Apply absolute session timeout': The API/data owner defines the minimum authorised response; application authorisation, object/field policy, gateway controls and backing-service permissions enforce exposure. Confirm named accountable teams during scoping. | AD8: For 'Apply absolute session timeout': The API product owner approves behaviour; application engineering changes logic; platform/IAM/gateway or data-service owners change policy and enforcement. Confirm named accountable teams during scoping. | AE8: For 'Apply absolute session timeout', execute or review as the representative low-privilege authenticated user, a different-role comparison user and an unauthenticated control client where the route is externally reachable. | AF8: Roles for 'Apply absolute session timeout': lowest intended consumer role; second role with different entitlement; unauthenticated control where exposed. Replace role classes with actual named roles during assessment setup. | AG8: Target mapping for 'Apply absolute session timeout': record the exact login/token/session/recovery/key endpoint, identity-provider/client policy and protected comparison API operation, including environment, version/build, host/base path and owner. Do not mark Ready until mapped. | AH8: Method for 'Apply absolute session timeout': capture an authorised baseline; modify only the control-relevant identity, identifier, field, header, parameter, state or trust input; compare status, body, timing, state and logs. Record variants and stop conditions before execution. | AI8: A low-privilege or out-of-context identity attempts to abuse 'apply absolute session timeout' by bypassing the intended control through alternate routes, contexts or malformed inputs to obtain unauthorised data, action, trust or service impact. | AJ8: Not directly applicable to this control. During route discovery, still confirm that any record-bearing request enforces object and tenant boundaries; otherwise cross-reference a dedicated BOLA test. | AK8: Repeat 'apply absolute session timeout' with the lowest authorised role and compare with the approved elevated role; verify server-side function, object, field and workflow-state authorisation. | AL8: For 'apply absolute session timeout', vary identifiers, duplicates, null/blank values, type and length boundaries, unsupported fields, encodings and safe malformed variants relevant to the parser; verify deterministic allowlisting and binding. | AM8: For 'apply absolute session timeout', compare returned or observable data with business need and role visibility; inspect fields, nested objects, metadata, error detail, timing, result limits, logs and cached artefacts for unnecessary disclosure. | AN8: Repeat 'apply absolute session timeout' without a session and using the public or guest context; verify no protected data, action, file, metadata or record-existence signal is available. | AO8: Review implementation evidence and execute a targeted API validation to verify: apply absolute session timeout. Confirm enforcement at the trusted server-side boundary and test negative/error behavior. | AP8: Use only authorised scope and synthetic or approved test data; stop immediately if protected real data is exposed or unexpected state change occurs; redact secrets and personal data from evidence. | AQ8: Restore the test object, account or session to its recorded baseline; delete synthetic records, tokens, links or files created solely for testing; confirm no queued job, callback or downstream operation remains pending. | AR8: For 'Apply absolute session timeout', protected behaviour is: the control operates consistently across intended and negative contexts, fails securely and leaves objective evidence. No unauthorised data, state change, trust expansion or sensitive diagnostic detail is produced. | AS8: PASS when the observed result matches the defined protected behaviour with no data, state, trust or availability weakness. FAIL when the result deviates from the protected behaviour or leaves the control unverifiable. Record the decision against 'apply absolute session timeout'. | AT8: The control for apply absolute session timeout is absent, inconsistently applied or bypassable, indicating a likely session management weakness across the affected target API and connected-service trust boundary. | AU8: A valid denial or compliant review for 'Apply absolute session timeout' suggests identity, credential, token or session validation is effective for the tested context. It does not prove alternate roles, routes, versions, batch paths or trust boundaries; validate the next representative variant. | AV8: Repeat 'Apply absolute session timeout' across a second role, alternate API/UI route, related object, batch/composite path and integration context; review telemetry and configuration for systemic coverage. | AW8: If 'Apply absolute session timeout' fails, likely impact includes account or service identity compromise and persistent unauthorised access. Primary affected parties: users, service principals and connected services. Current inherent severity is High; confirm exposure, data sensitivity, reachability and blast radius before final rating. | AX8: API2:2023 - Broken Authentication | AY8: A10:2025 - Mishandling of Exceptional Conditions | AZ8: SC | BA8: High | BB8: 16 | BC8: P1 - High | BD8: Candidate | BE8: Pending execution | BF8: Unassigned | BG8: Pending execution. Record the observed behaviour, affected data or state, and evidence-based pass/fail rationale. | BH8: Evidence for 'Apply absolute session timeout' must include: test ID, date, tester and environment; exact target/component and version; tested identity, role, entitlement and comparison context; expected result, actual result and decision rationale; redacted evidence links and relevant correlation or trace ID; authorised baseline request/response; control-relevant negative request/response; status, headers, body, timing and before/after state. | BI8: Pending execution: link or ID for requests, responses, screenshots, logs, artefacts and correlation records. | BJ8: Pending execution: identify the actual enforcing control or state that no effective control was observed. | BK8: Unassigned: assign only after scope confirmation or finding triage. | BL8: Not raised | BM8: Not Retested | BN8: Execution note for 'Apply absolute session timeout': replace all planning placeholders with observed evidence. This test is evidence-backed only for the executed route, role, method, data context and environment. Record untested variants, exclusions and residual risk. | BO8: https://owasp.org/API-Security/editions/2023/en/0x11-t10/ https://owasp.org/Top10/2025/ https://owasp.org/www-project-secure-coding-practices-quick-reference-guide/stable-en/02-checklist/05-checklist.html
A9: 1. Identity, Authentication & Session | B9: Session Lifecycle & Cookies | C9: API-IAM-008 | D9: Hybrid | E9: browser session, portal cookie and API session handling | F9: Apply idle timeout | G9: Verify that apply idle timeout is securely implemented for the scoped surface and cannot be bypassed by an unauthorised, lower-privilege or malformed request context. | H9: Applicable by default; mark N/A only with documented architecture or data-flow justification. | I9: Applicable if this authentication mechanism exists | J9: Execute when the scoped surface uses the referenced identity, token, session, credential or recovery capability. | K9: The capability for 'Apply idle timeout' is confirmed in scope; the exact route, component or configuration object and version are mapped; a successful authorised baseline has been captured; required valid and negative credential/session states are prepared and identity telemetry is accessible; evidence capture and redaction method are ready; authorisation and operational contacts are confirmed. | L9: Blocking prerequisites | M9: API-IAM-007 | N9: None identified | O9: Establish the baseline control behaviour for 'Session Lifecycle & Cookies' before testing this variant. | P9: Not Assessed | Q9: Wave 2 - Control Variants | R9: EVD-IAM-SESSION-LIFECYCL-BASE | S9: TDATA-IAM-SESSION-LIFECYCL-BASE | T9: API-IAM-007 | U9: PAR-W2-IAM | V9: Not waived | W9: Not applicable unless Dependency Gate is Waived. If waived, record approver, equivalent evidence, residual uncertainty and expiry/review date. | X9: Valid authenticated user; clean unauthenticated client; controlled invalid, expired, revoked or out-of-context credential variants as applicable. | Y9: Approved test account and controlled credential/token/session variants representing valid, invalid, expired, revoked, replayed and wrong-context states as applicable. | Z9: Authorised test environment representative of production security controls; production testing only where explicitly approved and operationally coordinated. | AA9: Shared responsibility | AB9: platform controls plus The organisation configuration/custom logic | AC9: For 'Apply idle timeout': The API/data owner defines the minimum authorised response; application authorisation, object/field policy, gateway controls and backing-service permissions enforce exposure. Confirm named accountable teams during scoping. | AD9: For 'Apply idle timeout': The API product owner approves behaviour; application engineering changes logic; platform/IAM/gateway or data-service owners change policy and enforcement. Confirm named accountable teams during scoping. | AE9: For 'Apply idle timeout', execute or review as the representative low-privilege authenticated user, a different-role comparison user and an unauthenticated control client where the route is externally reachable. | AF9: Roles for 'Apply idle timeout': lowest intended consumer role; second role with different entitlement; unauthenticated control where exposed. Replace role classes with actual named roles during assessment setup. | AG9: Target mapping for 'Apply idle timeout': record the exact login/token/session/recovery/key endpoint, identity-provider/client policy and protected comparison API operation, including environment, version/build, host/base path and owner. Do not mark Ready until mapped. | AH9: Method for 'Apply idle timeout': capture an authorised baseline; modify only the control-relevant identity, identifier, field, header, parameter, state or trust input; compare status, body, timing, state and logs. Record variants and stop conditions before execution. | AI9: A low-privilege or out-of-context identity attempts to abuse 'apply idle timeout' by bypassing the intended control through alternate routes, contexts or malformed inputs to obtain unauthorised data, action, trust or service impact. | AJ9: Not directly applicable to this control. During route discovery, still confirm that any record-bearing request enforces object and tenant boundaries; otherwise cross-reference a dedicated BOLA test. | AK9: Repeat 'apply idle timeout' with the lowest authorised role and compare with the approved elevated role; verify server-side function, object, field and workflow-state authorisation. | AL9: For 'apply idle timeout', vary identifiers, duplicates, null/blank values, type and length boundaries, unsupported fields, encodings and safe malformed variants relevant to the parser; verify deterministic allowlisting and binding. | AM9: For 'apply idle timeout', compare returned or observable data with business need and role visibility; inspect fields, nested objects, metadata, error detail, timing, result limits, logs and cached artefacts for unnecessary disclosure. | AN9: Repeat 'apply idle timeout' without a session and using the public or guest context; verify no protected data, action, file, metadata or record-existence signal is available. | AO9: Review implementation evidence and execute a targeted API validation to verify: apply idle timeout. Confirm enforcement at the trusted server-side boundary and test negative/error behavior. | AP9: Use only authorised scope and synthetic or approved test data; stop immediately if protected real data is exposed or unexpected state change occurs; redact secrets and personal data from evidence. | AQ9: Restore the test object, account or session to its recorded baseline; delete synthetic records, tokens, links or files created solely for testing; confirm no queued job, callback or downstream operation remains pending. | AR9: For 'Apply idle timeout', protected behaviour is: the control operates consistently across intended and negative contexts, fails securely and leaves objective evidence. No unauthorised data, state change, trust expansion or sensitive diagnostic detail is produced. | AS9: PASS when the observed result matches the defined protected behaviour with no data, state, trust or availability weakness. FAIL when the result deviates from the protected behaviour or leaves the control unverifiable. Record the decision against 'apply idle timeout'. | AT9: The control for apply idle timeout is absent, inconsistently applied or bypassable, indicating a likely session management weakness across the affected target API and connected-service trust boundary. | AU9: A valid denial or compliant review for 'Apply idle timeout' suggests identity, credential, token or session validation is effective for the tested context. It does not prove alternate roles, routes, versions, batch paths or trust boundaries; validate the next representative variant. | AV9: Repeat 'Apply idle timeout' across a second role, alternate API/UI route, related object, batch/composite path and integration context; review telemetry and configuration for systemic coverage. | AW9: If 'Apply idle timeout' fails, likely impact includes account or service identity compromise and persistent unauthorised access. Primary affected parties: users, service principals and connected services. Current inherent severity is High; confirm exposure, data sensitivity, reachability and blast radius before final rating. | AX9: API2:2023 - Broken Authentication | AY9: A10:2025 - Mishandling of Exceptional Conditions | AZ9: SC | BA9: High | BB9: 16 | BC9: P1 - High | BD9: Candidate | BE9: Pending execution | BF9: Unassigned | BG9: Pending execution. Record the observed behaviour, affected data or state, and evidence-based pass/fail rationale. | BH9: Evidence for 'Apply idle timeout' must include: test ID, date, tester and environment; exact target/component and version; tested identity, role, entitlement and comparison context; expected result, actual result and decision rationale; redacted evidence links and relevant correlation or trace ID; authorised baseline request/response; control-relevant negative request/response; status, headers, body, timing and before/after state. | BI9: Pending execution: link or ID for requests, responses, screenshots, logs, artefacts and correlation records. | BJ9: Pending execution: identify the actual enforcing control or state that no effective control was observed. | BK9: Unassigned: assign only after scope confirmation or finding triage. | BL9: Not raised | BM9: Not Retested | BN9: Execution note for 'Apply idle timeout': replace all planning placeholders with observed evidence. This test is evidence-backed only for the executed route, role, method, data context and environment. Record untested variants, exclusions and residual risk. | BO9: https://owasp.org/API-Security/editions/2023/en/0x11-t10/ https://owasp.org/Top10/2025/ https://owasp.org/www-project-secure-coding-practices-quick-reference-guide/stable-en/02-checklist/05-checklist.html
A10: 1. Identity, Authentication & Session | B10: Token Validation & JWT | C10: API-IAM-009 | D10: Hybrid | E10: application authentication, external identity provider, OAuth client and token-enabled API surface | F10: Authenticate sensitive external-system connections | G10: Verify that authenticate sensitive external-system connections is securely implemented for the scoped surface and cannot be bypassed by an unauthorised, lower-privilege or malformed request context. | H10: Applicable by default; mark N/A only with documented architecture or data-flow justification. | I10: Applicable if this authentication mechanism exists | J10: Execute when the scoped surface uses the referenced identity, token, session, credential or recovery capability. | K10: The capability for 'Authenticate sensitive external-system connections' is confirmed in scope; the exact route, component or configuration object and version are mapped; a successful authorised baseline has been captured; required valid and negative credential/session states are prepared and identity telemetry is accessible; evidence capture and redaction method are ready; authorisation and operational contacts are confirmed. | L10: Blocking prerequisites | M10: API-IAM-002 | N10: None identified | O10: Establish the baseline control behaviour for 'Token Validation & JWT' before testing this variant. | P10: Not Assessed | Q10: Wave 2 - Control Variants | R10: EVD-IAM-TOKEN-VALIDATION-BASE | S10: TDATA-IAM-TOKEN-VALIDATION-BASE | T10: API-IAM-002 | U10: PAR-W2-IAM | V10: Not waived | W10: Not applicable unless Dependency Gate is Waived. If waived, record approver, equivalent evidence, residual uncertainty and expiry/review date. | X10: Valid authenticated user; clean unauthenticated client; controlled invalid, expired, revoked or out-of-context credential variants as applicable. | Y10: Approved test account and controlled credential/token/session variants representing valid, invalid, expired, revoked, replayed and wrong-context states as applicable. | Z10: Authorised test environment representative of production security controls; production testing only where explicitly approved and operationally coordinated. | AA10: Shared responsibility | AB10: platform controls plus The organisation configuration/custom logic | AC10: For 'Authenticate sensitive external-system connections': The API/data owner defines the minimum authorised response; application authorisation, object/field policy, gateway controls and backing-service permissions enforce exposure. Confirm named accountable teams during scoping. | AD10: For 'Authenticate sensitive external-system connections': The API product owner approves behaviour; application engineering changes logic; platform/IAM/gateway or data-service owners change policy and enforcement. Confirm named accountable teams during scoping. | AE10: For 'Authenticate sensitive external-system connections', execute or review as the representative low-privilege authenticated user, a different-role comparison user and an unauthenticated control client where the route is externally reachable. | AF10: Roles for 'Authenticate sensitive external-system connections': lowest intended consumer role; second role with different entitlement; unauthenticated control where exposed. Replace role classes with actual named roles during assessment setup. | AG10: Target mapping for 'Authenticate sensitive external-system connections': record the exact login/token/session/recovery/key endpoint, identity-provider/client policy and protected comparison API operation, including environment, version/build, host/base path and owner. Do not mark Ready until mapped. | AH10: Method for 'Authenticate sensitive external-system connections': capture an authorised baseline; modify only the control-relevant identity, identifier, field, header, parameter, state or trust input; compare status, body, timing, state and logs. Record variants and stop conditions before execution. | AI10: A low-privilege or out-of-context identity attempts to abuse 'authenticate sensitive external-system connections' by requesting hidden fields, broader results, metadata or error detail to obtain unauthorised data, action, trust or service impact. | AJ10: Using two approved entitlement groups, repeat 'authenticate sensitive external-system connections' with an out-of-scope object, tenant, parent/child, file or business reference; verify access is derived from authenticated context rather than identifier knowledge. | AK10: Repeat 'authenticate sensitive external-system connections' with the lowest authorised role and compare with the approved elevated role; verify server-side function, object, field and workflow-state authorisation. | AL10: For 'authenticate sensitive external-system connections', vary identifiers, duplicates, null/blank values, type and length boundaries, unsupported fields, encodings and safe malformed variants relevant to the parser; verify deterministic allowlisting and binding. | AM10: For 'authenticate sensitive external-system connections', compare returned or observable data with business need and role visibility; inspect fields, nested objects, metadata, error detail, timing, result limits, logs and cached artefacts for unnecessary disclosure. | AN10: Repeat 'authenticate sensitive external-system connections' without a session and using the public or guest context; verify no protected data, action, file, metadata or record-existence signal is available. | AO10: Review implementation evidence and execute a targeted API validation to verify: authenticate sensitive external-system connections. Confirm enforcement at the trusted server-side boundary and test negative/error behavior. | AP10: Use only authorised scope and synthetic or approved test data; stop immediately if protected real data is exposed or unexpected state change occurs; redact secrets and personal data from evidence. | AQ10: Restore the test object, account or session to its recorded baseline; delete synthetic records, tokens, links or files created solely for testing; confirm no queued job, callback or downstream operation remains pending. | AR10: For 'Authenticate sensitive external-system connections', protected behaviour is: the control operates consistently across intended and negative contexts, fails securely and leaves objective evidence. No unauthorised data, state change, trust expansion or sensitive diagnostic detail is produced. | AS10: PASS when only necessary and authorised fields, metadata and errors are observable. FAIL when sensitive fields, internals, secrets or excessive results are exposed. Record the decision against 'authenticate sensitive external-system connections'. | AT10: The control for authenticate sensitive external-system connections is absent, inconsistently applied or bypassable, indicating a likely authentication and password management weakness across the affected target API and connected-service trust boundary. | AU10: A valid denial or compliant review for 'Authenticate sensitive external-system connections' suggests identity, credential, token or session validation is effective for the tested context. It does not prove alternate roles, routes, versions, batch paths or trust boundaries; validate the next representative variant. | AV10: Repeat 'Authenticate sensitive external-system connections' across a second role, alternate API/UI route, related object, batch/composite path and integration context; review telemetry and configuration for systemic coverage. | AW10: If 'Authenticate sensitive external-system connections' fails, likely impact includes account or service identity compromise and persistent unauthorised access. Primary affected parties: users, service principals and connected services. Current inherent severity is High; confirm exposure, data sensitivity, reachability and blast radius before final rating. | AX10: API2:2023 - Broken Authentication | AY10: A07:2025 - Authentication Failures | AZ10: IA | BA10: High | BB10: 16 | BC10: P1 - High | BD10: Candidate | BE10: Pending execution | BF10: Unassigned | BG10: Pending execution. Record the observed behaviour, affected data or state, and evidence-based pass/fail rationale. | BH10: Evidence for 'Authenticate sensitive external-system connections' must include: test ID, date, tester and environment; exact target/component and version; tested identity, role, entitlement and comparison context; expected result, actual result and decision rationale; redacted evidence links and relevant correlation or trace ID; authorised baseline request/response; control-relevant negative request/response; status, headers, body, timing and before/after state. | BI10: Pending execution: link or ID for requests, responses, screenshots, logs, artefacts and correlation records. | BJ10: Pending execution: identify the actual enforcing control or state that no effective control was observed. | BK10: Unassigned: assign only after scope confirmation or finding triage. | BL10: Not raised | BM10: Not Retested | BN10: Execution note for 'Authenticate sensitive external-system connections': replace all planning placeholders with observed evidence. This test is evidence-backed only for the executed route, role, method, data context and environment. Record untested variants, exclusions and residual risk. | BO10: https://owasp.org/API-Security/editions/2023/en/0x11-t10/ https://owasp.org/Top10/2025/ https://owasp.org/www-project-secure-coding-practices-quick-reference-guide/stable-en/02-checklist/05-checklist.html
A11: 1. Identity, Authentication & Session | B11: Token Validation & JWT | C11: API-IAM-010 | D11: Dynamic | E11: application authentication, external identity provider, OAuth client and token-enabled API surface | F11: Authentication over encrypted transport | G11: Verify that authentication over encrypted transport is securely implemented for the scoped surface and cannot be bypassed by an unauthorised, lower-privilege or malformed request context. | H11: Applicable when the API exposes the referenced capability or trust boundary. | I11: Applicable if this authentication mechanism exists | J11: Execute when the scoped surface uses the referenced identity, token, session, credential or recovery capability. | K11: The capability for 'Authentication over encrypted transport' is confirmed in scope; the exact route, component or configuration object and version are mapped; a successful authorised baseline has been captured; required valid and negative credential/session states are prepared and identity telemetry is accessible; evidence capture and redaction method are ready; authorisation and operational contacts are confirmed. | L11: Blocking prerequisites + non-blocking companions | M11: API-IAM-002 | N11: API-PROP-001, API-BFLA-001 | O11: Establish the baseline control behaviour for 'Token Validation & JWT' before testing this variant. Establish the minimum authorised response and field-visibility baseline. Use configuration baseline as corroborating evidence where available. | P11: Not Assessed | Q11: Wave 2 - Control Variants | R11: EVD-IAM-TOKEN-VALIDATION-BASE | S11: TDATA-IAM-TOKEN-VALIDATION-BASE | T11: API-IAM-002 | U11: PAR-W2-IAM | V11: Not waived | W11: Not applicable unless Dependency Gate is Waived. If waived, record approver, equivalent evidence, residual uncertainty and expiry/review date. | X11: Valid authenticated user; clean unauthenticated client; controlled invalid, expired, revoked or out-of-context credential variants as applicable. | Y11: Approved test account and controlled credential/token/session variants representing valid, invalid, expired, revoked, replayed and wrong-context states as applicable. | Z11: Authorised test environment representative of production security controls; production testing only where explicitly approved and operationally coordinated. | AA11: Shared responsibility | AB11: platform controls plus The organisation configuration/custom logic | AC11: For 'Authentication over encrypted transport': The API/data owner defines the minimum authorised response; application authorisation, object/field policy, gateway controls and backing-service permissions enforce exposure. Confirm named accountable teams during scoping. | AD11: For 'Authentication over encrypted transport': The API product owner approves behaviour; application engineering changes logic; platform/IAM/gateway or data-service owners change policy and enforcement. Confirm named accountable teams during scoping. | AE11: For 'Authentication over encrypted transport', execute or review as the representative low-privilege authenticated user, a different-role comparison user and an unauthenticated control client where the route is externally reachable. | AF11: Roles for 'Authentication over encrypted transport': lowest intended consumer role; second role with different entitlement; unauthenticated control where exposed. Replace role classes with actual named roles during assessment setup. | AG11: Target mapping for 'Authentication over encrypted transport': record the exact login/token/session/recovery/key endpoint, identity-provider/client policy and protected comparison API operation, including environment, version/build, host/base path and owner. Do not mark Ready until mapped. | AH11: Method for 'Authentication over encrypted transport': capture an authorised baseline; modify only the control-relevant identity, identifier, field, header, parameter, state or trust input; compare status, body, timing, state and logs. Record variants and stop conditions before execution. | AI11: A low-privilege or out-of-context identity attempts to abuse 'authentication over encrypted transport' by requesting hidden fields, broader results, metadata or error detail to obtain unauthorised data, action, trust or service impact. | AJ11: Using two approved entitlement groups, repeat 'authentication over encrypted transport' with an out-of-scope object, tenant, parent/child, file or business reference; verify access is derived from authenticated context rather than identifier knowledge. | AK11: Repeat 'authentication over encrypted transport' with the lowest authorised role and compare with the approved elevated role; verify server-side function, object, field and workflow-state authorisation. | AL11: For 'authentication over encrypted transport', vary identifiers, duplicates, null/blank values, type and length boundaries, unsupported fields, encodings and safe malformed variants relevant to the parser; verify deterministic allowlisting and binding. | AM11: For 'authentication over encrypted transport', compare returned or observable data with business need and role visibility; inspect fields, nested objects, metadata, error detail, timing, result limits, logs and cached artefacts for unnecessary disclosure. | AN11: Repeat 'authentication over encrypted transport' without a session and using the public or guest context; verify no protected data, action, file, metadata or record-existence signal is available. | AO11: Identify the relevant endpoint and baseline authorized behavior. Execute a controlled negative test for: authentication over encrypted transport. Compare authorization, state, response, timing, and audit evidence. | AP11: Use only authorised scope and synthetic or approved test data; stop immediately if protected real data is exposed or unexpected state change occurs; redact secrets and personal data from evidence. | AQ11: Restore the test object, account or session to its recorded baseline; delete synthetic records, tokens, links or files created solely for testing; confirm no queued job, callback or downstream operation remains pending. | AR11: For 'Authentication over encrypted transport', protected behaviour is: only necessary, authorised and correctly protected data or cryptographic material is observable. No unauthorised data, state change, trust expansion or sensitive diagnostic detail is produced. | AS11: PASS when only necessary and authorised fields, metadata and errors are observable. FAIL when sensitive fields, internals, secrets or excessive results are exposed. Record the decision against 'authentication over encrypted transport'. | AT11: The control for authentication over encrypted transport is absent, inconsistently applied or bypassable, indicating a likely authentication and password management weakness across the affected target API and connected-service trust boundary. | AU11: A valid denial or compliant review for 'Authentication over encrypted transport' suggests identity, credential, token or session validation is effective for the tested context. It does not prove alternate roles, routes, versions, batch paths or trust boundaries; validate the next representative variant. | AV11: Repeat 'Authentication over encrypted transport' across a second role, alternate API/UI route, related object, batch/composite path and integration context; review telemetry and configuration for systemic coverage. | AW11: If 'Authentication over encrypted transport' fails, likely impact includes account or service identity compromise and persistent unauthorised access, sensitive-data, document, secret or cryptographic material exposure. Primary affected parties: users, service principals and connected services, data subjects, legal/compliance stakeholders and information owners. Current inherent severity is High; confirm exposure, data sensitivity, reachability and blast radius before final rating. | AX11: API2:2023 - Broken Authentication | AY11: A07:2025 - Authentication Failures | AZ11: IA | BA11: High | BB11: 16 | BC11: P1 - High | BD11: Candidate | BE11: Pending execution | BF11: Unassigned | BG11: Pending execution. Record the observed behaviour, affected data or state, and evidence-based pass/fail rationale. | BH11: Evidence for 'Authentication over encrypted transport' must include: test ID, date, tester and environment; exact target/component and version; tested identity, role, entitlement and comparison context; expected result, actual result and decision rationale; redacted evidence links and relevant correlation or trace ID; authorised baseline request/response; control-relevant negative request/response; status, headers, body, timing and before/after state. | BI11: Pending execution: link or ID for requests, responses, screenshots, logs, artefacts and correlation records. | BJ11: Pending execution: identify the actual enforcing control or state that no effective control was observed. | BK11: Unassigned: assign only after scope confirmation or finding triage. | BL11: Not raised | BM11: Not Retested | BN11: Execution note for 'Authentication over encrypted transport': replace all planning placeholders with observed evidence. This test is evidence-backed only for the executed route, role, method, data context and environment. Record untested variants, exclusions and residual risk. | BO11: https://owasp.org/API-Security/editions/2023/en/0x11-t10/ https://owasp.org/Top10/2025/ https://owasp.org/www-project-secure-coding-practices-quick-reference-guide/stable-en/02-checklist/05-checklist.html
A12: 1. Identity, Authentication & Session | B12: Session Lifecycle & Cookies | C12: API-IAM-011 | D12: Hybrid | E12: browser session, portal cookie and API session handling | F12: Bind high-risk sessions to appropriate context | G12: Verify that bind high-risk sessions to appropriate context is securely implemented for the scoped surface and cannot be bypassed by an unauthorised, lower-privilege or malformed request context. | H12: Applicable by default; mark N/A only with documented architecture or data-flow justification. | I12: Applicable if this authentication mechanism exists | J12: Execute when the scoped surface uses the referenced identity, token, session, credential or recovery capability. | K12: The capability for 'Bind high-risk sessions to appropriate context' is confirmed in scope; the exact route, component or configuration object and version are mapped; a successful authorised baseline has been captured; required valid and negative credential/session states are prepared and identity telemetry is accessible; evidence capture and redaction method are ready; authorisation and operational contacts are confirmed. | L12: Blocking prerequisites | M12: API-IAM-007 | N12: None identified | O12: Establish the baseline control behaviour for 'Session Lifecycle & Cookies' before testing this variant. | P12: Not Assessed | Q12: Wave 2 - Control Variants | R12: EVD-IAM-SESSION-LIFECYCL-BASE | S12: TDATA-IAM-SESSION-LIFECYCL-BASE | T12: API-IAM-007 | U12: PAR-W2-IAM | V12: Not waived | W12: Not applicable unless Dependency Gate is Waived. If waived, record approver, equivalent evidence, residual uncertainty and expiry/review date. | X12: Valid authenticated user; clean unauthenticated client; controlled invalid, expired, revoked or out-of-context credential variants as applicable. | Y12: Approved test account and controlled credential/token/session variants representing valid, invalid, expired, revoked, replayed and wrong-context states as applicable. | Z12: Authorised test environment representative of production security controls; production testing only where explicitly approved and operationally coordinated. | AA12: Shared responsibility | AB12: platform controls plus The organisation configuration/custom logic | AC12: For 'Bind high-risk sessions to appropriate context': The API/data owner defines the minimum authorised response; application authorisation, object/field policy, gateway controls and backing-service permissions enforce exposure. Confirm named accountable teams during scoping. | AD12: For 'Bind high-risk sessions to appropriate context': The API product owner approves behaviour; application engineering changes logic; platform/IAM/gateway or data-service owners change policy and enforcement. Confirm named accountable teams during scoping. | AE12: For 'Bind high-risk sessions to appropriate context', execute or review as the representative low-privilege authenticated user, a different-role comparison user and an unauthenticated control client where the route is externally reachable. | AF12: Roles for 'Bind high-risk sessions to appropriate context': lowest intended consumer role; second role with different entitlement; unauthenticated control where exposed. Replace role classes with actual named roles during assessment setup. | AG12: Target mapping for 'Bind high-risk sessions to appropriate context': record the exact login/token/session/recovery/key endpoint, identity-provider/client policy and protected comparison API operation, including environment, version/build, host/base path and owner. Do not mark Ready until mapped. | AH12: Method for 'Bind high-risk sessions to appropriate context': capture an authorised baseline; modify only the control-relevant identity, identifier, field, header, parameter, state or trust input; compare status, body, timing, state and logs. Record variants and stop conditions before execution. | AI12: A low-privilege or out-of-context identity attempts to abuse 'bind high-risk sessions to appropriate context' by bypassing the intended control through alternate routes, contexts or malformed inputs to obtain unauthorised data, action, trust or service impact. | AJ12: Not directly applicable to this control. During route discovery, still confirm that any record-bearing request enforces object and tenant boundaries; otherwise cross-reference a dedicated BOLA test. | AK12: Repeat 'bind high-risk sessions to appropriate context' with the lowest authorised role and compare with the approved elevated role; verify server-side function, object, field and workflow-state authorisation. | AL12: For 'bind high-risk sessions to appropriate context', vary identifiers, duplicates, null/blank values, type and length boundaries, unsupported fields, encodings and safe malformed variants relevant to the parser; verify deterministic allowlisting and binding. | AM12: For 'bind high-risk sessions to appropriate context', compare returned or observable data with business need and role visibility; inspect fields, nested objects, metadata, error detail, timing, result limits, logs and cached artefacts for unnecessary disclosure. | AN12: Repeat 'bind high-risk sessions to appropriate context' without a session and using the public or guest context; verify no protected data, action, file, metadata or record-existence signal is available. | AO12: Review implementation evidence and execute a targeted API validation to verify: bind high-risk sessions to appropriate context. Confirm enforcement at the trusted server-side boundary and test negative/error behavior. | AP12: Use only authorised scope and synthetic or approved test data; stop immediately if protected real data is exposed or unexpected state change occurs; redact secrets and personal data from evidence. | AQ12: Restore the test object, account or session to its recorded baseline; delete synthetic records, tokens, links or files created solely for testing; confirm no queued job, callback or downstream operation remains pending. | AR12: For 'Bind high-risk sessions to appropriate context', protected behaviour is: the control operates consistently across intended and negative contexts, fails securely and leaves objective evidence. No unauthorised data, state change, trust expansion or sensitive diagnostic detail is produced. | AS12: PASS when the observed result matches the defined protected behaviour with no data, state, trust or availability weakness. FAIL when the result deviates from the protected behaviour or leaves the control unverifiable. Record the decision against 'bind high-risk sessions to appropriate context'. | AT12: The control for bind high-risk sessions to appropriate context is absent, inconsistently applied or bypassable, indicating a likely session management weakness across the affected target API and connected-service trust boundary. | AU12: A valid denial or compliant review for 'Bind high-risk sessions to appropriate context' suggests identity, credential, token or session validation is effective for the tested context. It does not prove alternate roles, routes, versions, batch paths or trust boundaries; validate the next representative variant. | AV12: Repeat 'Bind high-risk sessions to appropriate context' across a second role, alternate API/UI route, related object, batch/composite path and integration context; review telemetry and configuration for systemic coverage. | AW12: If 'Bind high-risk sessions to appropriate context' fails, likely impact includes account or service identity compromise and persistent unauthorised access. Primary affected parties: users, service principals and connected services. Current inherent severity is High; confirm exposure, data sensitivity, reachability and blast radius before final rating. | AX12: API2:2023 - Broken Authentication | AY12: A07:2025 - Authentication Failures | AZ12: IA, SC | BA12: High | BB12: 16 | BC12: P1 - High | BD12: Candidate | BE12: Pending execution | BF12: Unassigned | BG12: Pending execution. Record the observed behaviour, affected data or state, and evidence-based pass/fail rationale. | BH12: Evidence for 'Bind high-risk sessions to appropriate context' must include: test ID, date, tester and environment; exact target/component and version; tested identity, role, entitlement and comparison context; expected result, actual result and decision rationale; redacted evidence links and relevant correlation or trace ID; authorised baseline request/response; control-relevant negative request/response; status, headers, body, timing and before/after state. | BI12: Pending execution: link or ID for requests, responses, screenshots, logs, artefacts and correlation records. | BJ12: Pending execution: identify the actual enforcing control or state that no effective control was observed. | BK12: Unassigned: assign only after scope confirmation or finding triage. | BL12: Not raised | BM12: Not Retested | BN12: Execution note for 'Bind high-risk sessions to appropriate context': replace all planning placeholders with observed evidence. This test is evidence-backed only for the executed route, role, method, data context and environment. Record untested variants, exclusions and residual risk. | BO12: https://owasp.org/API-Security/editions/2023/en/0x11-t10/ https://owasp.org/Top10/2025/ https://owasp.org/www-project-secure-coding-practices-quick-reference-guide/stable-en/02-checklist/05-checklist.html
A13: 1. Identity, Authentication & Session | B13: Session Lifecycle & Cookies | C13: API-IAM-012 | D13: Hybrid | E13: browser session, portal cookie and API session handling | F13: Block caching of authenticated sensitive pages | G13: Verify that block caching of authenticated sensitive pages is securely implemented for the scoped surface and cannot be bypassed by an unauthorised, lower-privilege or malformed request context. | H13: Applicable by default; mark N/A only with documented architecture or data-flow justification. | I13: Applicable if this authentication mechanism exists | J13: Execute when the scoped surface uses the referenced identity, token, session, credential or recovery capability. | K13: The capability for 'Block caching of authenticated sensitive pages' is confirmed in scope; the exact route, component or configuration object and version are mapped; a successful authorised baseline has been captured; required valid and negative credential/session states are prepared and identity telemetry is accessible; evidence capture and redaction method are ready; authorisation and operational contacts are confirmed. | L13: Blocking prerequisites | M13: API-IAM-007 | N13: None identified | O13: Establish the baseline control behaviour for 'Session Lifecycle & Cookies' before testing this variant. | P13: Not Assessed | Q13: Wave 2 - Control Variants | R13: EVD-IAM-SESSION-LIFECYCL-BASE | S13: TDATA-IAM-SESSION-LIFECYCL-BASE | T13: API-IAM-007 | U13: PAR-W2-IAM | V13: Not waived | W13: Not applicable unless Dependency Gate is Waived. If waived, record approver, equivalent evidence, residual uncertainty and expiry/review date. | X13: Valid authenticated user; clean unauthenticated client; controlled invalid, expired, revoked or out-of-context credential variants as applicable. | Y13: Approved test account and controlled credential/token/session variants representing valid, invalid, expired, revoked, replayed and wrong-context states as applicable. | Z13: Authorised test environment representative of production security controls; production testing only where explicitly approved and operationally coordinated. | AA13: Shared responsibility | AB13: platform controls plus The organisation configuration/custom logic | AC13: For 'Block caching of authenticated sensitive pages': The API/data owner defines the minimum authorised response; application authorisation, object/field policy, gateway controls and backing-service permissions enforce exposure. Confirm named accountable teams during scoping. | AD13: For 'Block caching of authenticated sensitive pages': The API product owner approves behaviour; application engineering changes logic; platform/IAM/gateway or data-service owners change policy and enforcement. Confirm named accountable teams during scoping. | AE13: For 'Block caching of authenticated sensitive pages', execute or review as the representative low-privilege authenticated user, a different-role comparison user and an unauthenticated control client where the route is externally reachable. | AF13: Roles for 'Block caching of authenticated sensitive pages': lowest intended consumer role; second role with different entitlement; unauthenticated control where exposed. Replace role classes with actual named roles during assessment setup. | AG13: Target mapping for 'Block caching of authenticated sensitive pages': record the exact login/token/session/recovery/key endpoint, identity-provider/client policy and protected comparison API operation, including environment, version/build, host/base path and owner. Do not mark Ready until mapped. | AH13: Method for 'Block caching of authenticated sensitive pages': capture an authorised baseline; modify only the control-relevant identity, identifier, field, header, parameter, state or trust input; compare status, body, timing, state and logs. Record variants and stop conditions before execution. | AI13: A low-privilege or out-of-context identity attempts to abuse 'block caching of authenticated sensitive pages' by requesting hidden fields, broader results, metadata or error detail to obtain unauthorised data, action, trust or service impact. | AJ13: Using two approved entitlement groups, repeat 'block caching of authenticated sensitive pages' with an out-of-scope object, tenant, parent/child, file or business reference; verify access is derived from authenticated context rather than identifier knowledge. | AK13: Repeat 'block caching of authenticated sensitive pages' with the lowest authorised role and compare with the approved elevated role; verify server-side function, object, field and workflow-state authorisation. | AL13: For 'block caching of authenticated sensitive pages', vary identifiers, duplicates, null/blank values, type and length boundaries, unsupported fields, encodings and safe malformed variants relevant to the parser; verify deterministic allowlisting and binding. | AM13: For 'block caching of authenticated sensitive pages', compare returned or observable data with business need and role visibility; inspect fields, nested objects, metadata, error detail, timing, result limits, logs and cached artefacts for unnecessary disclosure. | AN13: Repeat 'block caching of authenticated sensitive pages' without a session and using the public or guest context; verify no protected data, action, file, metadata or record-existence signal is available. | AO13: Review implementation evidence and execute a targeted API validation to verify: block caching of authenticated sensitive pages. Confirm enforcement at the trusted server-side boundary and test negative/error behavior. | AP13: Use only authorised scope and synthetic or approved test data; stop immediately if protected real data is exposed or unexpected state change occurs; redact secrets and personal data from evidence. | AQ13: Restore the test object, account or session to its recorded baseline; delete synthetic records, tokens, links or files created solely for testing; confirm no queued job, callback or downstream operation remains pending. | AR13: For 'Block caching of authenticated sensitive pages', protected behaviour is: the control operates consistently across intended and negative contexts, fails securely and leaves objective evidence. No unauthorised data, state change, trust expansion or sensitive diagnostic detail is produced. | AS13: PASS when only necessary and authorised fields, metadata and errors are observable. FAIL when sensitive fields, internals, secrets or excessive results are exposed. Record the decision against 'block caching of authenticated sensitive pages'. | AT13: The control for block caching of authenticated sensitive pages is absent, inconsistently applied or bypassable, indicating a likely session management weakness across the affected target API and connected-service trust boundary. | AU13: A valid denial or compliant review for 'Block caching of authenticated sensitive pages' suggests identity, credential, token or session validation is effective for the tested context. It does not prove alternate roles, routes, versions, batch paths or trust boundaries; validate the next representative variant. | AV13: Repeat 'Block caching of authenticated sensitive pages' across a second role, alternate API/UI route, related object, batch/composite path and integration context; review telemetry and configuration for systemic coverage. | AW13: If 'Block caching of authenticated sensitive pages' fails, likely impact includes account or service identity compromise and persistent unauthorised access. Primary affected parties: users, service principals and connected services. Current inherent severity is High; confirm exposure, data sensitivity, reachability and blast radius before final rating. | AX13: API2:2023 - Broken Authentication | AY13: A07:2025 - Authentication Failures | AZ13: IA, SC | BA13: High | BB13: 16 | BC13: P1 - High | BD13: Candidate | BE13: Pending execution | BF13: Unassigned | BG13: Pending execution. Record the observed behaviour, affected data or state, and evidence-based pass/fail rationale. | BH13: Evidence for 'Block caching of authenticated sensitive pages' must include: test ID, date, tester and environment; exact target/component and version; tested identity, role, entitlement and comparison context; expected result, actual result and decision rationale; redacted evidence links and relevant correlation or trace ID; authorised baseline request/response; control-relevant negative request/response; status, headers, body, timing and before/after state. | BI13: Pending execution: link or ID for requests, responses, screenshots, logs, artefacts and correlation records. | BJ13: Pending execution: identify the actual enforcing control or state that no effective control was observed. | BK13: Unassigned: assign only after scope confirmation or finding triage. | BL13: Not raised | BM13: Not Retested | BN13: Execution note for 'Block caching of authenticated sensitive pages': replace all planning placeholders with observed evidence. This test is evidence-backed only for the executed route, role, method, data context and environment. Record untested variants, exclusions and residual risk. | BO13: https://owasp.org/API-Security/editions/2023/en/0x11-t10/ https://owasp.org/Top10/2025/ https://owasp.org/www-project-secure-coding-practices-quick-reference-guide/stable-en/02-checklist/05-checklist.html
... A484: 12. Client, Platform & General API Assurance | B484: Client-side Storage & Bootstrap Data | C484: API-PLATFORM-007 | D484: Hybrid | E484: DOM/bootstrap data exposure | F484: Validate portal DOM, bootstrap payloads, and client-side config do not expose hidden sensitive data or internal identifiers | G484: Verify that validate portal DOM, bootstrap payloads, and client-side config do not expose hidden sensitive data or internal identifiers is securely implemented for the scoped surface and cannot be bypassed by an unauthorised, lower-privilege or malformed request context. | H484: Applicable to the identified target application surface; confirm endpoint, role, data classification and environment before execution. | I484: Applicable if the referenced capability is exposed | J484: Confirm the feature, route, component or control exists in the authorised assessment scope before execution. | K484: The capability for 'Validate portal DOM, bootstrap payloads, and client-side config do not expose hidden sensitive data or internal identifiers' is confirmed in scope; the exact route, component or configuration object and version are mapped; a successful authorised baseline has been captured; two entitlement groups and known in-scope/out-of-scope object identifiers are available; evidence capture and redaction method are ready; authorisation and operational contacts are confirmed. | L484: Blocking prerequisites + non-blocking companions | M484: API-PLATFORM-004 | N484: API-IAM-032, API-PROP-001 | O484: Establish the baseline control behaviour for 'Client-side Storage & Bootstrap Data' before testing this variant. Establish valid baseline parsing and input constraints. Establish the minimum authorised response and field-visibility baseline. | P484: Not Assessed | Q484: Wave 2 - Control Variants | R484: EVD-PLATFORM-CLIENT-SIDE-STOR-BASE | S484: TDATA-PLATFORM-CLIENT-SIDE-STOR-BASE | T484: API-PLATFORM-004 | U484: PAR-W2-PLATFORM | V484: Not waived | W484: Not applicable unless Dependency Gate is Waived. If waived, record approver, equivalent evidence, residual uncertainty and expiry/review date. | X484: Two authorised users in separate tenant, account or entitlement groups; one owns or can access the target object and one must be denied. | Y484: Synthetic records in at least two entitlement groups, including one authorised object and one object that must remain inaccessible; known parent, child and reference identifiers where relevant. | Z484: Authorised test environment representative of production security controls; production testing only where explicitly approved and operationally coordinated. | AA484: Organisation-managed | AB484: The organisation development or platform team | AC484: For 'Validate portal DOM, bootstrap payloads, and client-side config do not expose hidden sensitive data or internal identifiers': The API/data owner defines the minimum authorised response; application authorisation, object/field policy, gateway controls and backing-service permissions enforce exposure. Confirm named accountable teams during scoping. | AD484: For 'Validate portal DOM, bootstrap payloads, and client-side config do not expose hidden sensitive data or internal identifiers': The API product owner approves behaviour; application engineering changes logic; platform/IAM/gateway or data-service owners change policy and enforcement. Confirm named accountable teams during scoping. | AE484: For 'Validate portal DOM, bootstrap payloads, and client-side config do not expose hidden sensitive data or internal identifiers', execute or review as the representative low-privilege authenticated user, a different-role comparison user and an unauthenticated control client where the route is externally reachable. | AF484: Roles for 'Validate portal DOM, bootstrap payloads, and client-side config do not expose hidden sensitive data or internal identifiers': lowest intended consumer role; second role with different entitlement; unauthenticated control where exposed. Replace role classes with actual named roles during assessment setup. | AG484: Target mapping for 'Validate portal DOM, bootstrap payloads, and client-side config do not expose hidden sensitive data or internal identifiers': record the exact route and HTTP operation or message action, controller/service method, gateway policy and backing data/service component, including environment, version/build, host/base path and owner. Do not mark Ready until mapped. | AH484: Method for 'Validate portal DOM, bootstrap payloads, and client-side config do not expose hidden sensitive data or internal identifiers': capture an authorised baseline; modify only the control-relevant identity, identifier, field, header, parameter, state or trust input; compare status, body, timing, state and logs. Record variants and stop conditions before execution. | AI484: A low-privilege or out-of-context identity attempts to abuse 'validate portal dom, bootstrap payloads, and client-side config do not expose hidden sensitive data or internal identifiers' by substituting object, tenant or relationship identifiers; altering request structure, types, lengths, encodings or query controls; requesting hidden fields, broader results, metadata or error detail to obtain unauthorised data, action, trust or service impact. | AJ484: Using two approved entitlement groups, repeat 'validate portal dom, bootstrap payloads, and client-side config do not expose hidden sensitive data or internal identifiers' with an out-of-scope object, tenant, parent/child, file or business reference; verify access is derived from authenticated context rather than identifier knowledge. | AK484: Repeat 'validate portal dom, bootstrap payloads, and client-side config do not expose hidden sensitive data or internal identifiers' with the lowest authorised role and compare with the approved elevated role; verify server-side function, object, field and workflow-state authorisation. | AL484: For 'validate portal dom, bootstrap payloads, and client-side config do not expose hidden sensitive data or internal identifiers', vary identifiers, duplicates, null/blank values, type and length boundaries, unsupported fields, encodings and safe malformed variants relevant to the parser; verify deterministic allowlisting and binding. | AM484: For 'validate portal dom, bootstrap payloads, and client-side config do not expose hidden sensitive data or internal identifiers', compare returned or observable data with business need and role visibility; inspect fields, nested objects, metadata, error detail, timing, result limits, logs and cached artefacts for unnecessary disclosure. | AN484: Repeat 'validate portal dom, bootstrap payloads, and client-side config do not expose hidden sensitive data or internal identifiers' without a session and using the public or guest context; verify no protected data, action, file, metadata or record-existence signal is available. | AO484: Inspect rendered HTML, bootstrap JSON, and client-side config for data beyond what the screen requires | AP484: Use only authorised scope and synthetic or approved test data; stop immediately if protected real data is exposed or unexpected state change occurs; redact secrets and personal data from evidence. | AQ484: Restore the test object, account or session to its recorded baseline; delete synthetic records, tokens, links or files created solely for testing; confirm no queued job, callback or downstream operation remains pending. | AR484: For 'Validate portal DOM, bootstrap payloads, and client-side config do not expose hidden sensitive data or internal identifiers', protected behaviour is: invalid or ambiguous input is rejected deterministically without scope expansion, execution or instability; only necessary, authorised and correctly protected data or cryptographic material is observable. No unauthorised data, state change, trust expansion or sensitive diagnostic detail is produced. | AS484: PASS when out-of-scope objects return denial or no protected data; malformed and unsupported input is rejected safely without expanding scope; only necessary and authorised fields, metadata and errors are observable. FAIL when any unauthorised cross-object or cross-tenant data is returned or changed; input changes policy, query scope, parser interpretation or server stability; sensitive fields, internals, secrets or excessive results are exposed. Record the decision against 'validate portal dom, bootstrap payloads, and client-side config do not expose hidden sensitive data or internal identifiers'. | AT484: Hidden data exposure, route discovery, or sensitivity leakage into the browser | AU484: A valid denial or compliant review for 'Validate portal DOM, bootstrap payloads, and client-side config do not expose hidden sensitive data or internal identifiers' suggests the intended platform, gateway, application or data-layer control is effective for the tested context. It does not prove alternate roles, routes, versions, batch paths or trust boundaries; validate the next representative variant. | AV484: Repeat 'Validate portal DOM, bootstrap payloads, and client-side config do not expose hidden sensitive data or internal identifiers' across a second role, alternate API/UI route, related object, batch/composite path and integration context; review telemetry and configuration for systemic coverage. | AW484: If 'Validate portal DOM, bootstrap payloads, and client-side config do not expose hidden sensitive data or internal identifiers' fails, likely impact includes sensitive-data, document, secret or cryptographic material exposure. Primary affected parties: data subjects, legal/compliance stakeholders and information owners. Current inherent severity is Medium; confirm exposure, data sensitivity, reachability and blast radius before final rating. | AX484: API3/API9 | AY484: A01/A05 | AZ484: AC, SC, SI | BA484: Medium | BB484: 9 | BC484: P2 - Planned | BD484: Candidate | BE484: Pending execution | BF484: Unassigned | BG484: Pending execution. Record the observed behaviour, affected data or state, and evidence-based pass/fail rationale. | BH484: Evidence for 'Validate portal DOM, bootstrap payloads, and client-side config do not expose hidden sensitive data or internal identifiers' must include: test ID, date, tester and environment; exact target/component and version; tested identity, role, entitlement and comparison context; expected result, actual result and decision rationale; redacted evidence links and relevant correlation or trace ID; authorised baseline request/response; control-relevant negative request/response; status, headers, body, timing and before/after state. | BI484: Pending execution: link or ID for requests, responses, screenshots, logs, artefacts and correlation records. | BJ484: Pending execution: identify the actual enforcing control or state that no effective control was observed. | BK484: Unassigned: assign only after scope confirmation or finding triage. | BL484: Not raised | BM484: Not Retested | BN484: Execution note for 'Validate portal DOM, bootstrap payloads, and client-side config do not expose hidden sensitive data or internal identifiers': replace all planning placeholders with observed evidence. This test is evidence-backed only for the executed route, role, method, data context and environment. Any unauthorised cross-user or cross-tenant data is High broken record-level access control at minimum. Record untested variants, exclusions and residual risk. | BO484: https://owasp.org/API-Security/editions/2023/en/0x11-t10/ https://owasp.org/Top10/2025/
